{
"meta":{"test_sets":[],"test_metrics":[],"learn_metrics":[{"best_value":"Min","name":"RMSE"}],"launch_mode":"Train","parameters":"","iteration_count":200,"learn_sets":["learn"],"name":"experiment"},
"iterations":[
{"learn":[0.03944914764],"iteration":0,"passed_time":0.004641718598,"remaining_time":0.9237020009},
{"learn":[0.03876636613],"iteration":1,"passed_time":0.008817697732,"remaining_time":0.8729520755},
{"learn":[0.03799171555],"iteration":2,"passed_time":0.01318495448,"remaining_time":0.8658120109},
{"learn":[0.03685846328],"iteration":3,"passed_time":0.01861539051,"remaining_time":0.9121541348},
{"learn":[0.03628141329],"iteration":4,"passed_time":0.02298558714,"remaining_time":0.8964378983},
{"learn":[0.0354520941],"iteration":5,"passed_time":0.02784316305,"remaining_time":0.9002622719},
{"learn":[0.03468556807],"iteration":6,"passed_time":0.03297026261,"remaining_time":0.9090372406},
{"learn":[0.03392082951],"iteration":7,"passed_time":0.03764994313,"remaining_time":0.9035986352},
{"learn":[0.03321648414],"iteration":8,"passed_time":0.04304603324,"remaining_time":0.9135324832},
{"learn":[0.0324720796],"iteration":9,"passed_time":0.04786122266,"remaining_time":0.9093632305},
{"learn":[0.03198264198],"iteration":10,"passed_time":0.05205807757,"remaining_time":0.8944524237},
{"learn":[0.03170519838],"iteration":11,"passed_time":0.05706782616,"remaining_time":0.8940626099},
{"learn":[0.03113085112],"iteration":12,"passed_time":0.06352737713,"remaining_time":0.9138168864},
{"learn":[0.03069082221],"iteration":13,"passed_time":0.06955119929,"remaining_time":0.924037362},
{"learn":[0.02989758865],"iteration":14,"passed_time":0.07461083461,"remaining_time":0.9202002935},
{"learn":[0.02933651168],"iteration":15,"passed_time":0.07874500933,"remaining_time":0.9055676073},
{"learn":[0.02866947669],"iteration":16,"passed_time":0.08398759454,"remaining_time":0.904101753},
{"learn":[0.02823859885],"iteration":17,"passed_time":0.08811188368,"remaining_time":0.8909090461},
{"learn":[0.02777400145],"iteration":18,"passed_time":0.09194887493,"remaining_time":0.8759340191},
{"learn":[0.02708448121],"iteration":19,"passed_time":0.09724553911,"remaining_time":0.875209852},
{"learn":[0.02686616216],"iteration":20,"passed_time":0.1023905033,"remaining_time":0.8727571475},
{"learn":[0.02651771963],"iteration":21,"passed_time":0.1077167764,"remaining_time":0.8715266454},
{"learn":[0.02613407929],"iteration":22,"passed_time":0.1127906726,"remaining_time":0.867997785},
{"learn":[0.02574934518],"iteration":23,"passed_time":0.1177165609,"remaining_time":0.8632547796},
{"learn":[0.02518553358],"iteration":24,"passed_time":0.1231806536,"remaining_time":0.8622645752},
{"learn":[0.0247696495],"iteration":25,"passed_time":0.1273586825,"remaining_time":0.8523234908},
{"learn":[0.02436337221],"iteration":26,"passed_time":0.1316830731,"remaining_time":0.843747098},
{"learn":[0.02401893662],"iteration":27,"passed_time":0.1356922202,"remaining_time":0.8335379242},
{"learn":[0.02360494808],"iteration":28,"passed_time":0.1397814804,"remaining_time":0.824228729},
{"learn":[0.02297663733],"iteration":29,"passed_time":0.144099901,"remaining_time":0.8165661057},
{"learn":[0.02262500616],"iteration":30,"passed_time":0.1488464325,"remaining_time":0.8114531322},
{"learn":[0.02213994286],"iteration":31,"passed_time":0.1528475764,"remaining_time":0.8024497759},
{"learn":[0.02186629301],"iteration":32,"passed_time":0.1565001113,"remaining_time":0.7919854119},
{"learn":[0.02144885521],"iteration":33,"passed_time":0.1608325953,"remaining_time":0.7852414949},
{"learn":[0.02109957983],"iteration":34,"passed_time":0.1647506812,"remaining_time":0.776681783},
{"learn":[0.02081753509],"iteration":35,"passed_time":0.1688228931,"remaining_time":0.7690820684},
{"learn":[0.02026350849],"iteration":36,"passed_time":0.1730014315,"remaining_time":0.7621414413},
{"learn":[0.01985002639],"iteration":37,"passed_time":0.1774729563,"remaining_time":0.7565952349},
{"learn":[0.0193927045],"iteration":38,"passed_time":0.1812745274,"remaining_time":0.7483384336},
{"learn":[0.0190205047],"iteration":39,"passed_time":0.1855147696,"remaining_time":0.7420590785},
{"learn":[0.01845543054],"iteration":40,"passed_time":0.1897168571,"remaining_time":0.7357312263},
{"learn":[0.01809392065],"iteration":41,"passed_time":0.1937457456,"remaining_time":0.728853043},
{"learn":[0.01777267312],"iteration":42,"passed_time":0.198134855,"remaining_time":0.7234226102},
{"learn":[0.01774150027],"iteration":43,"passed_time":0.1991984812,"remaining_time":0.7062491605},
{"learn":[0.01750569742],"iteration":44,"passed_time":0.2031071414,"remaining_time":0.6995912649},
{"learn":[0.01708581494],"iteration":45,"passed_time":0.2071968824,"remaining_time":0.6936591279},
{"learn":[0.01676199338],"iteration":46,"passed_time":0.2116309136,"remaining_time":0.6889261655},
{"learn":[0.01646520921],"iteration":47,"passed_time":0.2156541956,"remaining_time":0.6829049526},
{"learn":[0.0161724417],"iteration":48,"passed_time":0.219835116,"remaining_time":0.6774510716},
{"learn":[0.01594301966],"iteration":49,"passed_time":0.2239798702,"remaining_time":0.6719396106},
{"learn":[0.01578599959],"iteration":50,"passed_time":0.2280490356,"remaining_time":0.6662609079},
{"learn":[0.01541006786],"iteration":51,"passed_time":0.2323551272,"remaining_time":0.6613184388},
{"learn":[0.01524569899],"iteration":52,"passed_time":0.2367325758,"remaining_time":0.656597899},
{"learn":[0.01511743592],"iteration":53,"passed_time":0.2410147964,"remaining_time":0.6516325976},
{"learn":[0.01493245219],"iteration":54,"passed_time":0.2450873387,"remaining_time":0.6461393476},
{"learn":[0.01453996327],"iteration":55,"passed_time":0.2496957109,"remaining_time":0.6420746851},
{"learn":[0.01428251268],"iteration":56,"passed_time":0.253431102,"remaining_time":0.6358008349},
{"learn":[0.01406264127],"iteration":57,"passed_time":0.2575475273,"remaining_time":0.6305473943},
{"learn":[0.01393868327],"iteration":58,"passed_time":0.2615793835,"remaining_time":0.625130391},
{"learn":[0.01382107984],"iteration":59,"passed_time":0.2655248034,"remaining_time":0.6195578746},
{"learn":[0.0137434371],"iteration":60,"passed_time":0.2696681547,"remaining_time":0.6144897296},
{"learn":[0.01351622965],"iteration":61,"passed_time":0.2736355926,"remaining_time":0.6090598674},
{"learn":[0.01333188654],"iteration":62,"passed_time":0.2778284147,"remaining_time":0.6041665526},
{"learn":[0.0132173853],"iteration":63,"passed_time":0.2821022112,"remaining_time":0.5994671989},
{"learn":[0.01311015519],"iteration":64,"passed_time":0.286594711,"remaining_time":0.5952351689},
{"learn":[0.01281976389],"iteration":65,"passed_time":0.2915312179,"remaining_time":0.5918967152},
{"learn":[0.01252711857],"iteration":66,"passed_time":0.2968425659,"remaining_time":0.5892546458},
{"learn":[0.01236601588],"iteration":67,"passed_time":0.3026932208,"remaining_time":0.5875809581},
{"learn":[0.01214560313],"iteration":68,"passed_time":0.3080012461,"remaining_time":0.584755989},
{"learn":[0.0119645829],"iteration":69,"passed_time":0.3136432145,"remaining_time":0.5824802555},
{"learn":[0.01184309413],"iteration":70,"passed_time":0.3184861547,"remaining_time":0.5786579431},
{"learn":[0.01162830649],"iteration":71,"passed_time":0.3233345654,"remaining_time":0.5748170052},
{"learn":[0.01153856406],"iteration":72,"passed_time":0.3292208008,"remaining_time":0.5727539959},
{"learn":[0.01136517815],"iteration":73,"passed_time":0.3345822734,"remaining_time":0.5696941412},
{"learn":[0.01120311918],"iteration":74,"passed_time":0.3402502249,"remaining_time":0.5670837082},
{"learn":[0.01095994004],"iteration":75,"passed_time":0.3450058516,"remaining_time":0.5629042841},
{"learn":[0.01075476453],"iteration":76,"passed_time":0.3494721377,"remaining_time":0.5582477006},
{"learn":[0.01066992221],"iteration":77,"passed_time":0.3562847886,"remaining_time":0.5572659515},
{"learn":[0.01053652506],"iteration":78,"passed_time":0.3613087311,"remaining_time":0.5533969172},
{"learn":[0.01036401784],"iteration":79,"passed_time":0.3663177284,"remaining_time":0.5494765926},
{"learn":[0.01018167113],"iteration":80,"passed_time":0.3718240816,"remaining_time":0.5462600705},
{"learn":[0.00999982125],"iteration":81,"passed_time":0.3767768052,"remaining_time":0.5421910124},
{"learn":[0.009892839265],"iteration":82,"passed_time":0.3821586628,"remaining_time":0.5387055849},
{"learn":[0.009831111142],"iteration":83,"passed_time":0.3868342955,"remaining_time":0.5341997414},
{"learn":[0.009732636503],"iteration":84,"passed_time":0.3913536209,"remaining_time":0.5294784283},
{"learn":[0.009506740626],"iteration":85,"passed_time":0.3959967496,"remaining_time":0.5249259239},
{"learn":[0.009349677422],"iteration":86,"passed_time":0.4008688199,"remaining_time":0.5206686971},
{"learn":[0.009211649431],"iteration":87,"passed_time":0.4073035657,"remaining_time":0.5183863564},
{"learn":[0.009040834344],"iteration":88,"passed_time":0.4116408277,"remaining_time":0.5133947401},
{"learn":[0.008913096296],"iteration":89,"passed_time":0.4172463856,"remaining_time":0.5099678046},
{"learn":[0.008856337737],"iteration":90,"passed_time":0.4215105512,"remaining_time":0.5048862646},
{"learn":[0.008763543958],"iteration":91,"passed_time":0.4260351881,"remaining_time":0.5001282643},
{"learn":[0.008622708629],"iteration":92,"passed_time":0.4309460525,"remaining_time":0.4958196518},
{"learn":[0.008365906095],"iteration":93,"passed_time":0.4355715342,"remaining_time":0.4911764109},
{"learn":[0.008191617314],"iteration":94,"passed_time":0.4404102488,"remaining_time":0.4867692223},
{"learn":[0.008070720966],"iteration":95,"passed_time":0.4459433163,"remaining_time":0.4831052593},
{"learn":[0.007977871162],"iteration":96,"passed_time":0.4502967451,"remaining_time":0.478150152},
{"learn":[0.007770983732],"iteration":97,"passed_time":0.4543987364,"remaining_time":0.4729456236},
{"learn":[0.007689894653],"iteration":98,"passed_time":0.4587313195,"remaining_time":0.4679986188},
{"learn":[0.007602173255],"iteration":99,"passed_time":0.4633220484,"remaining_time":0.4633220484},
{"learn":[0.007509255249],"iteration":100,"passed_time":0.4688855403,"remaining_time":0.4596006782},
{"learn":[0.007423000487],"iteration":101,"passed_time":0.4730378313,"remaining_time":0.4544873281},
{"learn":[0.007265901143],"iteration":102,"passed_time":0.4776547615,"remaining_time":0.4498302123},
{"learn":[0.00707843837],"iteration":103,"passed_time":0.4821697396,"remaining_time":0.4450797596},
{"learn":[0.007003400846],"iteration":104,"passed_time":0.4863810775,"remaining_time":0.4400590701},
{"learn":[0.006914741131],"iteration":105,"passed_time":0.4909094317,"remaining_time":0.4353347791},
{"learn":[0.006789099368],"iteration":106,"passed_time":0.4963157438,"remaining_time":0.4313772353},
{"learn":[0.006702036995],"iteration":107,"passed_time":0.5011478825,"remaining_time":0.4269037517},
{"learn":[0.006619739272],"iteration":108,"passed_time":0.5060847189,"remaining_time":0.4225110956},
{"learn":[0.006527114675],"iteration":109,"passed_time":0.5110244512,"remaining_time":0.4181109146},
{"learn":[0.006451939757],"iteration":110,"passed_time":0.5157653745,"remaining_time":0.4135416066},
{"learn":[0.006395611554],"iteration":111,"passed_time":0.5209146737,"remaining_time":0.4092901008},
{"learn":[0.00627225348],"iteration":112,"passed_time":0.5254319145,"remaining_time":0.4045360758},
{"learn":[0.006120562809],"iteration":113,"passed_time":0.5298784741,"remaining_time":0.399732884},
{"learn":[0.006049810516],"iteration":114,"passed_time":0.5350643752,"remaining_time":0.3954823643},
{"learn":[0.005939072166],"iteration":115,"passed_time":0.5397016391,"remaining_time":0.3908184283},
{"learn":[0.005891191893],"iteration":116,"passed_time":0.544563904,"remaining_time":0.3863145643},
{"learn":[0.00581488031],"iteration":117,"passed_time":0.5497157685,"remaining_time":0.382005873},
{"learn":[0.005757505713],"iteration":118,"passed_time":0.5552433219,"remaining_time":0.3779387317},
{"learn":[0.005652951848],"iteration":119,"passed_time":0.560803785,"remaining_time":0.37386919},
{"learn":[0.005546234749],"iteration":120,"passed_time":0.5652345422,"remaining_time":0.3690374284},
{"learn":[0.005480638628],"iteration":121,"passed_time":0.5699759101,"remaining_time":0.3644108278},
{"learn":[0.005357648129],"iteration":122,"passed_time":0.575218315,"remaining_time":0.3600960184},
{"learn":[0.005260249832],"iteration":123,"passed_time":0.5792482063,"remaining_time":0.3550230942},
{"learn":[0.005230574686],"iteration":124,"passed_time":0.5835432785,"remaining_time":0.3501259671},
{"learn":[0.005150321692],"iteration":125,"passed_time":0.5876938193,"remaining_time":0.3451535129},
{"learn":[0.005089014894],"iteration":126,"passed_time":0.5916399328,"remaining_time":0.3400764968},
{"learn":[0.005046262407],"iteration":127,"passed_time":0.5958676529,"remaining_time":0.3351755547},
{"learn":[0.004964199357],"iteration":128,"passed_time":0.6004666681,"remaining_time":0.3304894064},
{"learn":[0.004902167695],"iteration":129,"passed_time":0.6047125783,"remaining_time":0.3256144652},
{"learn":[0.004834943961],"iteration":130,"passed_time":0.6092914025,"remaining_time":0.3209244792},
{"learn":[0.0047681856],"iteration":131,"passed_time":0.6142094477,"remaining_time":0.3164109276},
{"learn":[0.004736437036],"iteration":132,"passed_time":0.6186723683,"remaining_time":0.3116620201},
{"learn":[0.004650334146],"iteration":133,"passed_time":0.6231482415,"remaining_time":0.3069237607},
{"learn":[0.004600292316],"iteration":134,"passed_time":0.6273799281,"remaining_time":0.3020718172},
{"learn":[0.004522205215],"iteration":135,"passed_time":0.631552757,"remaining_time":0.2972012974},
{"learn":[0.004457850855],"iteration":136,"passed_time":0.6361980694,"remaining_time":0.2925582363},
{"learn":[0.004411270675],"iteration":137,"passed_time":0.6404479273,"remaining_time":0.2877374746},
{"learn":[0.004368459805],"iteration":138,"passed_time":0.644517635,"remaining_time":0.2828458686},
{"learn":[0.004297590357],"iteration":139,"passed_time":0.6488168226,"remaining_time":0.2780643525},
{"learn":[0.004231311965],"iteration":140,"passed_time":0.6529823293,"remaining_time":0.2732337406},
{"learn":[0.00418843505],"iteration":141,"passed_time":0.6571535756,"remaining_time":0.2684148407},
{"learn":[0.00413271008],"iteration":142,"passed_time":0.6617074675,"remaining_time":0.263757522},
{"learn":[0.004108781664],"iteration":143,"passed_time":0.6659742232,"remaining_time":0.2589899757},
{"learn":[0.004079455002],"iteration":144,"passed_time":0.6707585063,"remaining_time":0.2544256403},
{"learn":[0.004026685464],"iteration":145,"passed_time":0.6759196062,"remaining_time":0.2499976626},
{"learn":[0.003973513171],"iteration":146,"passed_time":0.6804802202,"remaining_time":0.2453432086},
{"learn":[0.003922210194],"iteration":147,"passed_time":0.6848892502,"remaining_time":0.2406367636},
{"learn":[0.003869794463],"iteration":148,"passed_time":0.6895286149,"remaining_time":0.23601315},
{"learn":[0.003838965555],"iteration":149,"passed_time":0.6938158326,"remaining_time":0.2312719442},
{"learn":[0.003792739157],"iteration":150,"passed_time":0.6980040582,"remaining_time":0.2265046281},
{"learn":[0.00377431008],"iteration":151,"passed_time":0.7025707302,"remaining_time":0.2218644411},
{"learn":[0.003733718791],"iteration":152,"passed_time":0.7071235501,"remaining_time":0.2172209598},
{"learn":[0.003684121828],"iteration":153,"passed_time":0.7112315013,"remaining_time":0.2124457731},
{"learn":[0.003644199296],"iteration":154,"passed_time":0.7162252931,"remaining_time":0.2079363754},
{"learn":[0.003604742679],"iteration":155,"passed_time":0.720876897,"remaining_time":0.203324253},
{"learn":[0.003555381595],"iteration":156,"passed_time":0.7249898273,"remaining_time":0.1985640928},
{"learn":[0.003533029006],"iteration":157,"passed_time":0.7290381784,"remaining_time":0.1937949588},
{"learn":[0.003494264104],"iteration":158,"passed_time":0.7330467345,"remaining_time":0.1890246296},
{"learn":[0.003443438941],"iteration":159,"passed_time":0.7370032645,"remaining_time":0.1842508161},
{"learn":[0.003421364274],"iteration":160,"passed_time":0.741126592,"remaining_time":0.1795275596},
{"learn":[0.003389762528],"iteration":161,"passed_time":0.7454372899,"remaining_time":0.1748556606},
{"learn":[0.003374796861],"iteration":162,"passed_time":0.7491269966,"remaining_time":0.1700472323},
{"learn":[0.003354926985],"iteration":163,"passed_time":0.7538669964,"remaining_time":0.1654829992},
{"learn":[0.003313444676],"iteration":164,"passed_time":0.7579278001,"remaining_time":0.1607725637},
{"learn":[0.003293222791],"iteration":165,"passed_time":0.7617778723,"remaining_time":0.1560267931},
{"learn":[0.003262704104],"iteration":166,"passed_time":0.766533549,"remaining_time":0.1514707013},
{"learn":[0.003240392437],"iteration":167,"passed_time":0.7704567734,"remaining_time":0.1467536711},
{"learn":[0.003207162299],"iteration":168,"passed_time":0.7747209549,"remaining_time":0.1421085775},
{"learn":[0.00317052508],"iteration":169,"passed_time":0.7801745304,"remaining_time":0.1376778583},
{"learn":[0.003144640554],"iteration":170,"passed_time":0.7845635082,"remaining_time":0.1330546301},
{"learn":[0.003128059893],"iteration":171,"passed_time":0.7886127508,"remaining_time":0.1283788199},
{"learn":[0.003103669476],"iteration":172,"passed_time":0.7942028044,"remaining_time":0.1239507267},
{"learn":[0.003084468655],"iteration":173,"passed_time":0.7984021874,"remaining_time":0.1193014763},
{"learn":[0.003070596472],"iteration":174,"passed_time":0.8027357932,"remaining_time":0.1146765419},
{"learn":[0.003033574186],"iteration":175,"passed_time":0.8069796801,"remaining_time":0.1100426837},
{"learn":[0.003009212761],"iteration":176,"passed_time":0.8112740996,"remaining_time":0.1054197982},
{"learn":[0.002990825155],"iteration":177,"passed_time":0.8155387723,"remaining_time":0.1007969269},
{"learn":[0.002964570084],"iteration":178,"passed_time":0.8197422121,"remaining_time":0.09617087404},
{"learn":[0.002953765974],"iteration":179,"passed_time":0.8240700269,"remaining_time":0.09156333633},
{"learn":[0.002939322931],"iteration":180,"passed_time":0.8282612175,"remaining_time":0.08694454769},
{"learn":[0.002921352434],"iteration":181,"passed_time":0.8325601647,"remaining_time":0.08234111519},
{"learn":[0.002897160681],"iteration":182,"passed_time":0.8366688571,"remaining_time":0.07772333645},
{"learn":[0.002872946572],"iteration":183,"passed_time":0.8410239987,"remaining_time":0.07313252163},
{"learn":[0.00285847786],"iteration":184,"passed_time":0.8450151974,"remaining_time":0.06851474573},
{"learn":[0.002838486394],"iteration":185,"passed_time":0.8488240405,"remaining_time":0.06388998154},
{"learn":[0.002812183441],"iteration":186,"passed_time":0.8530220913,"remaining_time":0.059301001},
{"learn":[0.002799462281],"iteration":187,"passed_time":0.8568810593,"remaining_time":0.0546945357},
{"learn":[0.002779443256],"iteration":188,"passed_time":0.8605525858,"remaining_time":0.05008507113},
{"learn":[0.002744503402],"iteration":189,"passed_time":0.8644058452,"remaining_time":0.04549504448},
{"learn":[0.002709119013],"iteration":190,"passed_time":0.8690466712,"remaining_time":0.04094984315},
{"learn":[0.002683178692],"iteration":191,"passed_time":0.8735015284,"remaining_time":0.03639589702},
{"learn":[0.002674338816],"iteration":192,"passed_time":0.8777499328,"remaining_time":0.03183548979},
{"learn":[0.002639126326],"iteration":193,"passed_time":0.8820132517,"remaining_time":0.02727876036},
{"learn":[0.002627792587],"iteration":194,"passed_time":0.8858415889,"remaining_time":0.02271388689},
{"learn":[0.002611567012],"iteration":195,"passed_time":0.8898942468,"remaining_time":0.01816110708},
{"learn":[0.002592985625],"iteration":196,"passed_time":0.8939461049,"remaining_time":0.01361339246},
{"learn":[0.002574124241],"iteration":197,"passed_time":0.8981640598,"remaining_time":0.00907236424},
{"learn":[0.002555216935],"iteration":198,"passed_time":0.9019929866,"remaining_time":0.004532628073},
{"learn":[0.002544566573],"iteration":199,"passed_time":0.9065267158,"remaining_time":0}
]}