{
    "success": true,
    "stock_data": {
        "symbol": "ANANTRAJ.NS",
        "name": "ANANT RAJ LIMITED",
        "current_price": {
            "INR": 581.55,
            "USD": 6.72,
            "EUR": 5.72,
            "BTC": 5.821e-05,
            "ETH": 0.00185463
        },
        "sector": "Real Estate",
        "industry": "Real Estate - Development",
        "pe_ratio": 46.748394,
        "dividends": 0.13
    },
    "recommendation": "STRONG SELL",
    "buy_score": -0.36961575548026326,
    "sell_score": 0.46961575548026324,
    "technical_indicators": {
        "sma_50": 553.7076104736328,
        "sma_200": 617.3866438293458,
        "ema_50": 552.3143843383906,
        "rsi": 56.965815943893055,
        "macd": 8.786824578177288,
        "signal_line": 10.276284419032164,
        "macd_histogram": -1.4894598408548756,
        "bb_upper": 608.8276606676307,
        "bb_lower": 527.32024582651,
        "volatility": 0.022546005580106818,
        "momentum": 0.05375081770319821,
        "volume_trend": "HIGH"
    },
    "fundamental_analysis": {
        "market_cap": 199623426048,
        "pe_ratio": 46.748394,
        "dividend_yield": 13.0,
        "52w_high": 947.9,
        "52w_low": 376.15,
        "balance_sheet": {
            "Ordinary Shares Number": {
                "2025-03-31 00:00:00": 343260616.0,
                "2024-03-31 00:00:00": 341890753.0,
                "2023-03-31 00:00:00": 324096335.0,
                "2022-03-31 00:00:00": 295096335.0,
                "2021-03-31 00:00:00": null
            },
            "Share Issued": {
                "2025-03-31 00:00:00": 343260616.0,
                "2024-03-31 00:00:00": 341890753.0,
                "2023-03-31 00:00:00": 324096335.0,
                "2022-03-31 00:00:00": 295096335.0,
                "2021-03-31 00:00:00": null
            },
            "Net Debt": {
                "2025-03-31 00:00:00": 1366400000.0,
                "2024-03-31 00:00:00": 3217347000.0,
                "2023-03-31 00:00:00": 10453948000.0,
                "2022-03-31 00:00:00": 12735326000.0,
                "2021-03-31 00:00:00": null
            },
            "Total Debt": {
                "2025-03-31 00:00:00": 4815900000.0,
                "2024-03-31 00:00:00": 6267441000.0,
                "2023-03-31 00:00:00": 10794581000.0,
                "2022-03-31 00:00:00": 12929633000.0,
                "2021-03-31 00:00:00": null
            },
            "Tangible Book Value": {
                "2025-03-31 00:00:00": 41607900000.0,
                "2024-03-31 00:00:00": 36563565000.0,
                "2023-03-31 00:00:00": 28250797000.0,
                "2022-03-31 00:00:00": 26391002000.0,
                "2021-03-31 00:00:00": null
            },
            "Invested Capital": {
                "2025-03-31 00:00:00": 46274500000.0,
                "2024-03-31 00:00:00": 42831006000.0,
                "2023-03-31 00:00:00": 39045378000.0,
                "2022-03-31 00:00:00": 39320635000.0,
                "2021-03-31 00:00:00": null
            },
            "Working Capital": {
                "2025-03-31 00:00:00": 21717900000.0,
                "2024-03-31 00:00:00": 22737809000.0,
                "2023-03-31 00:00:00": 17970078000.0,
                "2022-03-31 00:00:00": 15576845000.0,
                "2021-03-31 00:00:00": null
            },
            "Net Tangible Assets": {
                "2025-03-31 00:00:00": 41607900000.0,
                "2024-03-31 00:00:00": 36563565000.0,
                "2023-03-31 00:00:00": 28250797000.0,
                "2022-03-31 00:00:00": 26391002000.0,
                "2021-03-31 00:00:00": null
            },
            "Capital Lease Obligations": {
                "2025-03-31 00:00:00": 149300000.0,
                "2024-03-31 00:00:00": null,
                "2023-03-31 00:00:00": null,
                "2022-03-31 00:00:00": null,
                "2021-03-31 00:00:00": null
            },
            "Common Stock Equity": {
                "2025-03-31 00:00:00": 41607900000.0,
                "2024-03-31 00:00:00": 36563565000.0,
                "2023-03-31 00:00:00": 28250797000.0,
                "2022-03-31 00:00:00": 26391002000.0,
                "2021-03-31 00:00:00": null
            },
            "Total Capitalization": {
                "2025-03-31 00:00:00": 45499800000.0,
                "2024-03-31 00:00:00": 41237367000.0,
                "2023-03-31 00:00:00": 36994595000.0,
                "2022-03-31 00:00:00": 35491770000.0,
                "2021-03-31 00:00:00": null
            },
            "Total Equity Gross Minority Interest": {
                "2025-03-31 00:00:00": 41886800000.0,
                "2024-03-31 00:00:00": 36845349000.0,
                "2023-03-31 00:00:00": 28582816000.0,
                "2022-03-31 00:00:00": 26744248000.0,
                "2021-03-31 00:00:00": null
            },
            "Minority Interest": {
                "2025-03-31 00:00:00": 278900000.0,
                "2024-03-31 00:00:00": 281784000.0,
                "2023-03-31 00:00:00": 332019000.0,
                "2022-03-31 00:00:00": 353246000.0,
                "2021-03-31 00:00:00": null
            },
            "Stockholders Equity": {
                "2025-03-31 00:00:00": 41607900000.0,
                "2024-03-31 00:00:00": 36563565000.0,
                "2023-03-31 00:00:00": 28250797000.0,
                "2022-03-31 00:00:00": 26391002000.0,
                "2021-03-31 00:00:00": null
            },
            "Other Equity Interest": {
                "2025-03-31 00:00:00": 40921400000.0,
                "2024-03-31 00:00:00": -10902000.0,
                "2023-03-31 00:00:00": 28167000.0,
                "2022-03-31 00:00:00": 1236707000.0,
                "2021-03-31 00:00:00": null
            },
            "Retained Earnings": {
                "2025-03-31 00:00:00": null,
                "2024-03-31 00:00:00": 16368758000.0,
                "2023-03-31 00:00:00": 13950293000.0,
                "2022-03-31 00:00:00": 12658139000.0,
                "2021-03-31 00:00:00": 12699224000.0
            },
            "Additional Paid In Capital": {
                "2025-03-31 00:00:00": null,
                "2024-03-31 00:00:00": 13162302000.0,
                "2023-03-31 00:00:00": 7414149000.0,
                "2022-03-31 00:00:00": 5837999000.0,
                "2021-03-31 00:00:00": 5837999000.0
            },
            "Capital Stock": {
                "2025-03-31 00:00:00": 686500000.0,
                "2024-03-31 00:00:00": 683782000.0,
                "2023-03-31 00:00:00": 648193000.0,
                "2022-03-31 00:00:00": 590193000.0,
                "2021-03-31 00:00:00": null
            },
            "Common Stock": {
                "2025-03-31 00:00:00": 686500000.0,
                "2024-03-31 00:00:00": 683782000.0,
                "2023-03-31 00:00:00": 648193000.0,
                "2022-03-31 00:00:00": 590193000.0,
                "2021-03-31 00:00:00": null
            },
            "Total Liabilities Net Minority Interest": {
                "2025-03-31 00:00:00": 10458400000.0,
                "2024-03-31 00:00:00": 11837325000.0,
                "2023-03-31 00:00:00": 14982952000.0,
                "2022-03-31 00:00:00": 17105776000.0,
                "2021-03-31 00:00:00": null
            },
            "Total Non Current Liabilities Net Minority Interest": {
                "2025-03-31 00:00:00": 5555800000.0,
                "2024-03-31 00:00:00": 7194655000.0,
                "2023-03-31 00:00:00": 11179049000.0,
                "2022-03-31 00:00:00": 10948102000.0,
                "2021-03-31 00:00:00": null
            },
            "Other Non Current Liabilities": {
                "2025-03-31 00:00:00": 973800000.0,
                "2024-03-31 00:00:00": 376399000.0,
                "2023-03-31 00:00:00": 684401000.0,
                "2022-03-31 00:00:00": 1574635000.0,
                "2021-03-31 00:00:00": null
            },
            "Non Current Pension And Other Postretirement Benefit Plans": {
                "2025-03-31 00:00:00": null,
                "2024-03-31 00:00:00": 25721000.0,
                "2023-03-31 00:00:00": 20068000.0,
                "2022-03-31 00:00:00": null,
                "2021-03-31 00:00:00": null
            },
            "Non Current Accrued Expenses": {
                "2025-03-31 00:00:00": null,
                "2024-03-31 00:00:00": 0.0,
                "2023-03-31 00:00:00": 0.0,
                "2022-03-31 00:00:00": null,
                "2021-03-31 00:00:00": null
            },
            "Tradeand Other Payables Non Current": {
                "2025-03-31 00:00:00": null,
                "2024-03-31 00:00:00": 1297000.0,
                "2023-03-31 00:00:00": 225099000.0,
                "2022-03-31 00:00:00": null,
                "2021-03-31 00:00:00": null
            },
            "Non Current Deferred Revenue": {
                "2025-03-31 00:00:00": null,
                "2024-03-31 00:00:00": 1400678000.0,
                "2023-03-31 00:00:00": 915387000.0,
                "2022-03-31 00:00:00": null,
                "2021-03-31 00:00:00": 243417000.0
            },
            "Non Current Deferred Taxes Liabilities": {
                "2025-03-31 00:00:00": 377700000.0,
                "2024-03-31 00:00:00": 512485000.0,
                "2023-03-31 00:00:00": 373737000.0,
                "2022-03-31 00:00:00": 251139000.0,
                "2021-03-31 00:00:00": null
            },
            "Long Term Debt And Capital Lease Obligation": {
                "2025-03-31 00:00:00": 4029500000.0,
                "2024-03-31 00:00:00": 4673802000.0,
                "2023-03-31 00:00:00": 8743798000.0,
                "2022-03-31 00:00:00": 9100768000.0,
                "2021-03-31 00:00:00": null
            },
            "Long Term Capital Lease Obligation": {
                "2025-03-31 00:00:00": 137600000.0,
                "2024-03-31 00:00:00": null,
                "2023-03-31 00:00:00": null,
                "2022-03-31 00:00:00": null,
                "2021-03-31 00:00:00": null
            },
            "Long Term Debt": {
                "2025-03-31 00:00:00": 3891900000.0,
                "2024-03-31 00:00:00": 4673802000.0,
                "2023-03-31 00:00:00": 8743798000.0,
                "2022-03-31 00:00:00": 9100768000.0,
                "2021-03-31 00:00:00": null
            },
            "Long Term Provisions": {
                "2025-03-31 00:00:00": 31500000.0,
                "2024-03-31 00:00:00": 25700000.0,
                "2023-03-31 00:00:00": 20100000.0,
                "2022-03-31 00:00:00": 21560000.0,
                "2021-03-31 00:00:00": null
            },
            "Current Liabilities": {
                "2025-03-31 00:00:00": 4902600000.0,
                "2024-03-31 00:00:00": 4642670000.0,
                "2023-03-31 00:00:00": 3803903000.0,
                "2022-03-31 00:00:00": 6157674000.0,
                "2021-03-31 00:00:00": null
            },
            "Other Current Liabilities": {
                "2025-03-31 00:00:00": 3461000000.0,
                "2024-03-31 00:00:00": 2776500000.0,
                "2023-03-31 00:00:00": 2946200000.0,
                "2022-03-31 00:00:00": 28320000.0,
                "2021-03-31 00:00:00": null
            },
            "Current Debt And Capital Lease Obligation": {
                "2025-03-31 00:00:00": 786400000.0,
                "2024-03-31 00:00:00": 1593639000.0,
                "2023-03-31 00:00:00": 2050783000.0,
                "2022-03-31 00:00:00": 3828865000.0,
                "2021-03-31 00:00:00": null
            },
            "Current Capital Lease Obligation": {
                "2025-03-31 00:00:00": 11700000.0,
                "2024-03-31 00:00:00": null,
                "2023-03-31 00:00:00": null,
                "2022-03-31 00:00:00": null,
                "2021-03-31 00:00:00": null
            },
            "Current Debt": {
                "2025-03-31 00:00:00": 774700000.0,
                "2024-03-31 00:00:00": 1593639000.0,
                "2023-03-31 00:00:00": 2050783000.0,
                "2022-03-31 00:00:00": 3828865000.0,
                "2021-03-31 00:00:00": null
            },
            "Pensionand Other Post Retirement Benefit Plans Current": {
                "2025-03-31 00:00:00": null,
                "2024-03-31 00:00:00": 11420000.0,
                "2023-03-31 00:00:00": 9063000.0,
                "2022-03-31 00:00:00": 9878000.0,
                "2021-03-31 00:00:00": 8125000.0
            },
            "Current Provisions": {
                "2025-03-31 00:00:00": 12900000.0,
                "2024-03-31 00:00:00": 11400000.0,
                "2023-03-31 00:00:00": 9100000.0,
                "2022-03-31 00:00:00": 9878000.0,
                "2021-03-31 00:00:00": null
            },
            "Payables": {
                "2025-03-31 00:00:00": 553100000.0,
                "2024-03-31 00:00:00": 598124000.0,
                "2023-03-31 00:00:00": 792351000.0,
                "2022-03-31 00:00:00": 737722000.0,
                "2021-03-31 00:00:00": null
            },
            "Other Payable": {
                "2025-03-31 00:00:00": null,
                "2024-03-31 00:00:00": 335224000.0,
                "2023-03-31 00:00:00": 320469000.0,
                "2022-03-31 00:00:00": 429743000.0,
                "2021-03-31 00:00:00": 1434910000.0
            },
            "Dividends Payable": {
                "2025-03-31 00:00:00": null,
                "2024-03-31 00:00:00": 2026000.0,
                "2023-03-31 00:00:00": 2231000.0,
                "2022-03-31 00:00:00": 2714000.0,
                "2021-03-31 00:00:00": 2829000.0
            },
            "Total Tax Payable": {
                "2025-03-31 00:00:00": 352400000.0,
                "2024-03-31 00:00:00": 68890000.0,
                "2023-03-31 00:00:00": 333302000.0,
                "2022-03-31 00:00:00": 245571000.0,
                "2021-03-31 00:00:00": null
            },
            "Accounts Payable": {
                "2025-03-31 00:00:00": 200700000.0,
                "2024-03-31 00:00:00": 191984000.0,
                "2023-03-31 00:00:00": 136349000.0,
                "2022-03-31 00:00:00": 59694000.0,
                "2021-03-31 00:00:00": null
            },
            "Total Assets": {
                "2025-03-31 00:00:00": 52345200000.0,
                "2024-03-31 00:00:00": 48682674000.0,
                "2023-03-31 00:00:00": 43565768000.0,
                "2022-03-31 00:00:00": 43850024000.0,
                "2021-03-31 00:00:00": null
            },
            "Total Non Current Assets": {
                "2025-03-31 00:00:00": 25724700000.0,
                "2024-03-31 00:00:00": 21302195000.0,
                "2023-03-31 00:00:00": 21791787000.0,
                "2022-03-31 00:00:00": 22115505000.0,
                "2021-03-31 00:00:00": null
            },
            "Other Non Current Assets": {
                "2025-03-31 00:00:00": 3452500000.0,
                "2024-03-31 00:00:00": 2647600000.0,
                "2023-03-31 00:00:00": 2085600000.0,
                "2022-03-31 00:00:00": 2420100000.0,
                "2021-03-31 00:00:00": null
            },
            "Non Current Prepaid Assets": {
                "2025-03-31 00:00:00": null,
                "2024-03-31 00:00:00": 1419900000.0,
                "2023-03-31 00:00:00": 1729544000.0,
                "2022-03-31 00:00:00": 1389429000.0,
                "2021-03-31 00:00:00": 1596722000.0
            },
            "Investmentin Financial Assets": {
                "2025-03-31 00:00:00": 6742500000.0,
                "2024-03-31 00:00:00": 3018406000.0,
                "2023-03-31 00:00:00": 4602587000.0,
                "2022-03-31 00:00:00": 4602498000.0,
                "2021-03-31 00:00:00": null
            },
            "Available For Sale Securities": {
                "2025-03-31 00:00:00": 6742500000.0,
                "2024-03-31 00:00:00": 3018406000.0,
                "2023-03-31 00:00:00": 4573264000.0,
                "2022-03-31 00:00:00": 4574730000.0,
                "2021-03-31 00:00:00": null
            },
            "Trading Securities": {
                "2025-03-31 00:00:00": null,
                "2024-03-31 00:00:00": 0.0,
                "2023-03-31 00:00:00": 29323000.0,
                "2022-03-31 00:00:00": 27768000.0,
                "2021-03-31 00:00:00": 26616000.0
            },
            "Investment Properties": {
                "2025-03-31 00:00:00": 12516000000.0,
                "2024-03-31 00:00:00": 12427547000.0,
                "2023-03-31 00:00:00": 12560143000.0,
                "2022-03-31 00:00:00": 12696258000.0,
                "2021-03-31 00:00:00": null
            },
            "Goodwill And Other Intangible Assets": {
                "2025-03-31 00:00:00": null,
                "2024-03-31 00:00:00": null,
                "2023-03-31 00:00:00": null,
                "2022-03-31 00:00:00": null,
                "2021-03-31 00:00:00": 0.0
            },
            "Goodwill": {
                "2025-03-31 00:00:00": null,
                "2024-03-31 00:00:00": null,
                "2023-03-31 00:00:00": null,
                "2022-03-31 00:00:00": null,
                "2021-03-31 00:00:00": 0.0
            },
            "Net PPE": {
                "2025-03-31 00:00:00": 1520800000.0,
                "2024-03-31 00:00:00": 925236000.0,
                "2023-03-31 00:00:00": 677754000.0,
                "2022-03-31 00:00:00": 879835000.0,
                "2021-03-31 00:00:00": null
            },
            "Accumulated Depreciation": {
                "2025-03-31 00:00:00": null,
                "2024-03-31 00:00:00": -675803000.0,
                "2023-03-31 00:00:00": -638122000.0,
                "2022-03-31 00:00:00": -639988000.0,
                "2021-03-31 00:00:00": -614470000.0
            },
            "Gross PPE": {
                "2025-03-31 00:00:00": 1520800000.0,
                "2024-03-31 00:00:00": 1601039000.0,
                "2023-03-31 00:00:00": 1315876000.0,
                "2022-03-31 00:00:00": 1519823000.0,
                "2021-03-31 00:00:00": null
            },
            "Construction In Progress": {
                "2025-03-31 00:00:00": 363500000.0,
                "2024-03-31 00:00:00": 214955000.0,
                "2023-03-31 00:00:00": 184956000.0,
                "2022-03-31 00:00:00": 475602000.0,
                "2021-03-31 00:00:00": null
            },
            "Other Properties": {
                "2025-03-31 00:00:00": 1157300000.0,
                "2024-03-31 00:00:00": 710300000.0,
                "2023-03-31 00:00:00": 492800000.0,
                "2022-03-31 00:00:00": 404200000.0,
                "2021-03-31 00:00:00": null
            },
            "Machinery Furniture Equipment": {
                "2025-03-31 00:00:00": null,
                "2024-03-31 00:00:00": 1080945000.0,
                "2023-03-31 00:00:00": 866832000.0,
                "2022-03-31 00:00:00": 788250000.0,
                "2021-03-31 00:00:00": 780044000.0
            },
            "Buildings And Improvements": {
                "2025-03-31 00:00:00": null,
                "2024-03-31 00:00:00": 149862000.0,
                "2023-03-31 00:00:00": 19051000.0,
                "2022-03-31 00:00:00": 10934000.0,
                "2021-03-31 00:00:00": 10934000.0
            },
            "Land And Improvements": {
                "2025-03-31 00:00:00": null,
                "2024-03-31 00:00:00": 155277000.0,
                "2023-03-31 00:00:00": 245037000.0,
                "2022-03-31 00:00:00": 245037000.0,
                "2021-03-31 00:00:00": 253497000.0
            },
            "Properties": {
                "2025-03-31 00:00:00": null,
                "2024-03-31 00:00:00": 0.0,
                "2023-03-31 00:00:00": 0.0,
                "2022-03-31 00:00:00": 0.0,
                "2021-03-31 00:00:00": 0.0
            },
            "Current Assets": {
                "2025-03-31 00:00:00": 26620500000.0,
                "2024-03-31 00:00:00": 27380479000.0,
                "2023-03-31 00:00:00": 21773981000.0,
                "2022-03-31 00:00:00": 21734519000.0,
                "2021-03-31 00:00:00": null
            },
            "Other Current Assets": {
                "2025-03-31 00:00:00": 894700000.0,
                "2024-03-31 00:00:00": 1267000000.0,
                "2023-03-31 00:00:00": 1145900000.0,
                "2022-03-31 00:00:00": 333729000.0,
                "2021-03-31 00:00:00": null
            },
            "Restricted Cash": {
                "2025-03-31 00:00:00": null,
                "2024-03-31 00:00:00": 162230000.0,
                "2023-03-31 00:00:00": 143279000.0,
                "2022-03-31 00:00:00": 113859000.0,
                "2021-03-31 00:00:00": 104931000.0
            },
            "Prepaid Assets": {
                "2025-03-31 00:00:00": null,
                "2024-03-31 00:00:00": 524210000.0,
                "2023-03-31 00:00:00": 642157000.0,
                "2022-03-31 00:00:00": 326533000.0,
                "2021-03-31 00:00:00": 190654000.0
            },
            "Inventory": {
                "2025-03-31 00:00:00": 11512600000.0,
                "2024-03-31 00:00:00": 14158510000.0,
                "2023-03-31 00:00:00": 11967213000.0,
                "2022-03-31 00:00:00": 11349148000.0,
                "2021-03-31 00:00:00": null
            },
            "Other Inventories": {
                "2025-03-31 00:00:00": null,
                "2024-03-31 00:00:00": 19790000.0,
                "2023-03-31 00:00:00": 14004000.0,
                "2022-03-31 00:00:00": 11785000.0,
                "2021-03-31 00:00:00": 11785000.0
            },
            "Finished Goods": {
                "2025-03-31 00:00:00": null,
                "2024-03-31 00:00:00": 14138720000.0,
                "2023-03-31 00:00:00": 11953209000.0,
                "2022-03-31 00:00:00": 11337363000.0,
                "2021-03-31 00:00:00": 14554609000.0
            },
            "Other Receivables": {
                "2025-03-31 00:00:00": null,
                "2024-03-31 00:00:00": 8488962000.0,
                "2023-03-31 00:00:00": 7961212000.0,
                "2022-03-31 00:00:00": 9199159000.0,
                "2021-03-31 00:00:00": 8237178000.0
            },
            "Accounts Receivable": {
                "2025-03-31 00:00:00": 1258000000.0,
                "2024-03-31 00:00:00": 996443000.0,
                "2023-03-31 00:00:00": 512792000.0,
                "2022-03-31 00:00:00": 217784000.0,
                "2021-03-31 00:00:00": null
            },
            "Cash Cash Equivalents And Short Term Investments": {
                "2025-03-31 00:00:00": 12955200000.0,
                "2024-03-31 00:00:00": 3050124000.0,
                "2023-03-31 00:00:00": 547328000.0,
                "2022-03-31 00:00:00": 194307000.0,
                "2021-03-31 00:00:00": null
            },
            "Other Short Term Investments": {
                "2025-03-31 00:00:00": 9655000000.0,
                "2024-03-31 00:00:00": 30000.0,
                "2023-03-31 00:00:00": 206695000.0,
                "2022-03-31 00:00:00": 8093900000.0,
                "2021-03-31 00:00:00": null
            },
            "Cash And Cash Equivalents": {
                "2025-03-31 00:00:00": 3300200000.0,
                "2024-03-31 00:00:00": 3050094000.0,
                "2023-03-31 00:00:00": 340633000.0,
                "2022-03-31 00:00:00": 194307000.0,
                "2021-03-31 00:00:00": null
            },
            "Cash Equivalents": {
                "2025-03-31 00:00:00": null,
                "2024-03-31 00:00:00": 1624125000.0,
                "2023-03-31 00:00:00": 42871000.0,
                "2022-03-31 00:00:00": 82407000.0,
                "2021-03-31 00:00:00": 132181000.0
            },
            "Cash Financial": {
                "2025-03-31 00:00:00": null,
                "2024-03-31 00:00:00": 1425969000.0,
                "2023-03-31 00:00:00": 297762000.0,
                "2022-03-31 00:00:00": 111900000.0,
                "2021-03-31 00:00:00": 136501000.0
            }
        },
        "income_statement": {
            "Tax Effect Of Unusual Items": {
                "2025-03-31 00:00:00": 0.0,
                "2024-03-31 00:00:00": 0.0,
                "2023-03-31 00:00:00": 6593736.667868,
                "2022-03-31 00:00:00": 0.0,
                "2021-03-31 00:00:00": null
            },
            "Tax Rate For Calcs": {
                "2025-03-31 00:00:00": 0.140644,
                "2024-03-31 00:00:00": 0.169628,
                "2023-03-31 00:00:00": 0.265887,
                "2022-03-31 00:00:00": 0.322287,
                "2021-03-31 00:00:00": null
            },
            "Normalized EBITDA": {
                "2025-03-31 00:00:00": 5319800000.0,
                "2024-03-31 00:00:00": 3712500000.0,
                "2023-03-31 00:00:00": 2421288000.0,
                "2022-03-31 00:00:00": 1152600000.0,
                "2021-03-31 00:00:00": null
            },
            "Total Unusual Items": {
                "2025-03-31 00:00:00": 0.0,
                "2024-03-31 00:00:00": 0.0,
                "2023-03-31 00:00:00": 24799000.0,
                "2022-03-31 00:00:00": 0.0,
                "2021-03-31 00:00:00": null
            },
            "Total Unusual Items Excluding Goodwill": {
                "2025-03-31 00:00:00": 0.0,
                "2024-03-31 00:00:00": 0.0,
                "2023-03-31 00:00:00": 24799000.0,
                "2022-03-31 00:00:00": 0.0,
                "2021-03-31 00:00:00": null
            },
            "Net Income From Continuing Operation Net Minority Interest": {
                "2025-03-31 00:00:00": 4255400000.0,
                "2024-03-31 00:00:00": 2609100000.0,
                "2023-03-31 00:00:00": 1511163000.0,
                "2022-03-31 00:00:00": 565200000.0,
                "2021-03-31 00:00:00": null
            },
            "Reconciled Depreciation": {
                "2025-03-31 00:00:00": 304600000.0,
                "2024-03-31 00:00:00": 180600000.0,
                "2023-03-31 00:00:00": 165085000.0,
                "2022-03-31 00:00:00": 166700000.0,
                "2021-03-31 00:00:00": null
            },
            "Reconciled Cost Of Revenue": {
                "2025-03-31 00:00:00": 14827300000.0,
                "2024-03-31 00:00:00": 10799700000.0,
                "2023-03-31 00:00:00": 7096003000.0,
                "2022-03-31 00:00:00": 3469800000.0,
                "2021-03-31 00:00:00": null
            },
            "EBITDA": {
                "2025-03-31 00:00:00": 5319800000.0,
                "2024-03-31 00:00:00": 3712500000.0,
                "2023-03-31 00:00:00": 2446087000.0,
                "2022-03-31 00:00:00": 1152600000.0,
                "2021-03-31 00:00:00": null
            },
            "EBIT": {
                "2025-03-31 00:00:00": 5015200000.0,
                "2024-03-31 00:00:00": 3531900000.0,
                "2023-03-31 00:00:00": 2281002000.0,
                "2022-03-31 00:00:00": 985900000.0,
                "2021-03-31 00:00:00": null
            },
            "Net Interest Income": {
                "2025-03-31 00:00:00": -109900000.0,
                "2024-03-31 00:00:00": -346100000.0,
                "2023-03-31 00:00:00": 97655000.0,
                "2022-03-31 00:00:00": -270700000.0,
                "2021-03-31 00:00:00": null
            },
            "Interest Expense": {
                "2025-03-31 00:00:00": 109900000.0,
                "2024-03-31 00:00:00": 346100000.0,
                "2023-03-31 00:00:00": 313931000.0,
                "2022-03-31 00:00:00": 270700000.0,
                "2021-03-31 00:00:00": null
            },
            "Interest Income": {
                "2025-03-31 00:00:00": null,
                "2024-03-31 00:00:00": 332217000.0,
                "2023-03-31 00:00:00": 415285000.0,
                "2022-03-31 00:00:00": 361519000.0,
                "2021-03-31 00:00:00": 190514000.0
            },
            "Normalized Income": {
                "2025-03-31 00:00:00": 4255400000.0,
                "2024-03-31 00:00:00": 2609100000.0,
                "2023-03-31 00:00:00": 1492957736.667868,
                "2022-03-31 00:00:00": 565200000.0,
                "2021-03-31 00:00:00": null
            },
            "Net Income From Continuing And Discontinued Operation": {
                "2025-03-31 00:00:00": 4255400000.0,
                "2024-03-31 00:00:00": 2609100000.0,
                "2023-03-31 00:00:00": 1511163000.0,
                "2022-03-31 00:00:00": 565200000.0,
                "2021-03-31 00:00:00": null
            },
            "Total Expenses": {
                "2025-03-31 00:00:00": 15987600000.0,
                "2024-03-31 00:00:00": 11675500000.0,
                "2023-03-31 00:00:00": 7763915000.0,
                "2022-03-31 00:00:00": 4026500000.0,
                "2021-03-31 00:00:00": null
            },
            "Rent Expense Supplemental": {
                "2025-03-31 00:00:00": null,
                "2024-03-31 00:00:00": 20758000.0,
                "2023-03-31 00:00:00": 11278000.0,
                "2022-03-31 00:00:00": 8705000.0,
                "2021-03-31 00:00:00": 11463000.0
            },
            "Diluted Average Shares": {
                "2025-03-31 00:00:00": null,
                "2024-03-31 00:00:00": 327776382.0,
                "2023-03-31 00:00:00": 324096335.0,
                "2022-03-31 00:00:00": 324827586.0,
                "2021-03-31 00:00:00": 295096335.0
            },
            "Basic Average Shares": {
                "2025-03-31 00:00:00": null,
                "2024-03-31 00:00:00": 327776382.0,
                "2023-03-31 00:00:00": 324096335.0,
                "2022-03-31 00:00:00": 294375000.0,
                "2021-03-31 00:00:00": 295096335.0
            },
            "Diluted EPS": {
                "2025-03-31 00:00:00": null,
                "2024-03-31 00:00:00": 7.96,
                "2023-03-31 00:00:00": 4.662697,
                "2022-03-31 00:00:00": 1.74,
                "2021-03-31 00:00:00": 0.43
            },
            "Basic EPS": {
                "2025-03-31 00:00:00": null,
                "2024-03-31 00:00:00": 7.96,
                "2023-03-31 00:00:00": 4.662697,
                "2022-03-31 00:00:00": 1.92,
                "2021-03-31 00:00:00": 0.43
            },
            "Diluted NI Availto Com Stockholders": {
                "2025-03-31 00:00:00": 4255400000.0,
                "2024-03-31 00:00:00": 2609100000.0,
                "2023-03-31 00:00:00": 1511163000.0,
                "2022-03-31 00:00:00": 565200000.0,
                "2021-03-31 00:00:00": null
            },
            "Net Income Common Stockholders": {
                "2025-03-31 00:00:00": 4255400000.0,
                "2024-03-31 00:00:00": 2609100000.0,
                "2023-03-31 00:00:00": 1511163000.0,
                "2022-03-31 00:00:00": 565200000.0,
                "2021-03-31 00:00:00": null
            },
            "Otherunder Preferred Stock Dividend": {
                "2025-03-31 00:00:00": 0.0,
                "2024-03-31 00:00:00": 0.0,
                "2023-03-31 00:00:00": 0.0,
                "2022-03-31 00:00:00": 0.0,
                "2021-03-31 00:00:00": null
            },
            "Net Income": {
                "2025-03-31 00:00:00": 4255400000.0,
                "2024-03-31 00:00:00": 2609100000.0,
                "2023-03-31 00:00:00": 1511163000.0,
                "2022-03-31 00:00:00": 565200000.0,
                "2021-03-31 00:00:00": null
            },
            "Minority Interests": {
                "2025-03-31 00:00:00": -2800000.0,
                "2024-03-31 00:00:00": -50200000.0,
                "2023-03-31 00:00:00": 21083000.0,
                "2022-03-31 00:00:00": 16300000.0,
                "2021-03-31 00:00:00": null
            },
            "Net Income Including Noncontrolling Interests": {
                "2025-03-31 00:00:00": 4258200000.0,
                "2024-03-31 00:00:00": 2659300000.0,
                "2023-03-31 00:00:00": 1490080000.0,
                "2022-03-31 00:00:00": 548900000.0,
                "2021-03-31 00:00:00": null
            },
            "Net Income Continuous Operations": {
                "2025-03-31 00:00:00": 4258200000.0,
                "2024-03-31 00:00:00": 2659300000.0,
                "2023-03-31 00:00:00": 1490080000.0,
                "2022-03-31 00:00:00": 548900000.0,
                "2021-03-31 00:00:00": null
            },
            "Tax Provision": {
                "2025-03-31 00:00:00": 689900000.0,
                "2024-03-31 00:00:00": 540400000.0,
                "2023-03-31 00:00:00": 523019000.0,
                "2022-03-31 00:00:00": 230500000.0,
                "2021-03-31 00:00:00": null
            },
            "Pretax Income": {
                "2025-03-31 00:00:00": 4905300000.0,
                "2024-03-31 00:00:00": 3185800000.0,
                "2023-03-31 00:00:00": 1967071000.0,
                "2022-03-31 00:00:00": 715200000.0,
                "2021-03-31 00:00:00": null
            },
            "Other Non Operating Income Expenses": {
                "2025-03-31 00:00:00": 403100000.0,
                "2024-03-31 00:00:00": 374400000.0,
                "2023-03-31 00:00:00": 39105000.0,
                "2022-03-31 00:00:00": 393800000.0,
                "2021-03-31 00:00:00": null
            },
            "Special Income Charges": {
                "2025-03-31 00:00:00": 0.0,
                "2024-03-31 00:00:00": 0.0,
                "2023-03-31 00:00:00": 0.0,
                "2022-03-31 00:00:00": 0.0,
                "2021-03-31 00:00:00": null
            },
            "Net Non Operating Interest Income Expense": {
                "2025-03-31 00:00:00": -109900000.0,
                "2024-03-31 00:00:00": -346100000.0,
                "2023-03-31 00:00:00": 97655000.0,
                "2022-03-31 00:00:00": -270700000.0,
                "2021-03-31 00:00:00": null
            },
            "Total Other Finance Cost": {
                "2025-03-31 00:00:00": null,
                "2024-03-31 00:00:00": 14608000.0,
                "2023-03-31 00:00:00": 3699000.0,
                "2022-03-31 00:00:00": 4470000.0,
                "2021-03-31 00:00:00": 18269000.0
            },
            "Interest Expense Non Operating": {
                "2025-03-31 00:00:00": 109900000.0,
                "2024-03-31 00:00:00": 346100000.0,
                "2023-03-31 00:00:00": 313931000.0,
                "2022-03-31 00:00:00": 270700000.0,
                "2021-03-31 00:00:00": null
            },
            "Interest Income Non Operating": {
                "2025-03-31 00:00:00": null,
                "2024-03-31 00:00:00": 332217000.0,
                "2023-03-31 00:00:00": 415285000.0,
                "2022-03-31 00:00:00": 361519000.0,
                "2021-03-31 00:00:00": 190514000.0
            },
            "Operating Income": {
                "2025-03-31 00:00:00": 4612100000.0,
                "2024-03-31 00:00:00": 3157500000.0,
                "2023-03-31 00:00:00": 1805512000.0,
                "2022-03-31 00:00:00": 592100000.0,
                "2021-03-31 00:00:00": null
            },
            "Operating Expense": {
                "2025-03-31 00:00:00": 1160300000.0,
                "2024-03-31 00:00:00": 875800000.0,
                "2023-03-31 00:00:00": 667912000.0,
                "2022-03-31 00:00:00": 556700000.0,
                "2021-03-31 00:00:00": null
            },
            "Other Operating Expenses": {
                "2025-03-31 00:00:00": 632500000.0,
                "2024-03-31 00:00:00": 503200000.0,
                "2023-03-31 00:00:00": 217641000.0,
                "2022-03-31 00:00:00": 248200000.0,
                "2021-03-31 00:00:00": null
            },
            "Depreciation And Amortization In Income Statement": {
                "2025-03-31 00:00:00": 304600000.0,
                "2024-03-31 00:00:00": 180600000.0,
                "2023-03-31 00:00:00": 165085000.0,
                "2022-03-31 00:00:00": 166700000.0,
                "2021-03-31 00:00:00": null
            },
            "Depreciation Income Statement": {
                "2025-03-31 00:00:00": 304600000.0,
                "2024-03-31 00:00:00": 180600000.0,
                "2023-03-31 00:00:00": 165085000.0,
                "2022-03-31 00:00:00": 166700000.0,
                "2021-03-31 00:00:00": null
            },
            "Selling General And Administration": {
                "2025-03-31 00:00:00": null,
                "2024-03-31 00:00:00": 116184000.0,
                "2023-03-31 00:00:00": 117257000.0,
                "2022-03-31 00:00:00": 97061000.0,
                "2021-03-31 00:00:00": 77966000.0
            },
            "Selling And Marketing Expense": {
                "2025-03-31 00:00:00": null,
                "2024-03-31 00:00:00": 53886000.0,
                "2023-03-31 00:00:00": 58701000.0,
                "2022-03-31 00:00:00": 46568000.0,
                "2021-03-31 00:00:00": 41032000.0
            },
            "General And Administrative Expense": {
                "2025-03-31 00:00:00": null,
                "2024-03-31 00:00:00": 62298000.0,
                "2023-03-31 00:00:00": 58556000.0,
                "2022-03-31 00:00:00": 50493000.0,
                "2021-03-31 00:00:00": 36934000.0
            },
            "Rent And Landing Fees": {
                "2025-03-31 00:00:00": null,
                "2024-03-31 00:00:00": 20758000.0,
                "2023-03-31 00:00:00": 11278000.0,
                "2022-03-31 00:00:00": 8705000.0,
                "2021-03-31 00:00:00": 11463000.0
            },
            "Gross Profit": {
                "2025-03-31 00:00:00": 5772400000.0,
                "2024-03-31 00:00:00": 4033300000.0,
                "2023-03-31 00:00:00": 2473424000.0,
                "2022-03-31 00:00:00": 1148800000.0,
                "2021-03-31 00:00:00": null
            },
            "Cost Of Revenue": {
                "2025-03-31 00:00:00": 14827300000.0,
                "2024-03-31 00:00:00": 10799700000.0,
                "2023-03-31 00:00:00": 7096003000.0,
                "2022-03-31 00:00:00": 3469800000.0,
                "2021-03-31 00:00:00": null
            },
            "Total Revenue": {
                "2025-03-31 00:00:00": 20599700000.0,
                "2024-03-31 00:00:00": 14833000000.0,
                "2023-03-31 00:00:00": 9569427000.0,
                "2022-03-31 00:00:00": 4618600000.0,
                "2021-03-31 00:00:00": null
            },
            "Operating Revenue": {
                "2025-03-31 00:00:00": 20599700000.0,
                "2024-03-31 00:00:00": 14833000000.0,
                "2023-03-31 00:00:00": 9569427000.0,
                "2022-03-31 00:00:00": 4618600000.0,
                "2021-03-31 00:00:00": null
            }
        },
        "cash_flow": {
            "Free Cash Flow": {
                "2025-03-31 00:00:00": 196000000.0,
                "2024-03-31 00:00:00": -694800000.0,
                "2023-03-31 00:00:00": -89257000.0,
                "2022-03-31 00:00:00": 4222100000.0,
                "2021-03-31 00:00:00": null
            },
            "Issuance Of Capital Stock": {
                "2025-03-31 00:00:00": 2700000.0,
                "2024-03-31 00:00:00": 35600000.0,
                "2023-03-31 00:00:00": 425610000.0,
                "2022-03-31 00:00:00": 1236700000.0,
                "2021-03-31 00:00:00": null
            },
            "Capital Expenditure": {
                "2025-03-31 00:00:00": -770100000.0,
                "2024-03-31 00:00:00": -439600000.0,
                "2023-03-31 00:00:00": -418054000.0,
                "2022-03-31 00:00:00": -10700000.0,
                "2021-03-31 00:00:00": null
            },
            "End Cash Position": {
                "2025-03-31 00:00:00": 3300200000.0,
                "2024-03-31 00:00:00": 3050100000.0,
                "2023-03-31 00:00:00": 340633000.0,
                "2022-03-31 00:00:00": 194300000.0,
                "2021-03-31 00:00:00": null
            },
            "Other Cash Adjustment Outside Changein Cash": {
                "2025-03-31 00:00:00": null,
                "2024-03-31 00:00:00": null,
                "2023-03-31 00:00:00": null,
                "2022-03-31 00:00:00": null,
                "2021-03-31 00:00:00": 100000.0
            },
            "Beginning Cash Position": {
                "2025-03-31 00:00:00": 3050100000.0,
                "2024-03-31 00:00:00": 340600000.0,
                "2023-03-31 00:00:00": 194307000.0,
                "2022-03-31 00:00:00": 268700000.0,
                "2021-03-31 00:00:00": null
            },
            "Changes In Cash": {
                "2025-03-31 00:00:00": 250100000.0,
                "2024-03-31 00:00:00": 2709500000.0,
                "2023-03-31 00:00:00": 146326000.0,
                "2022-03-31 00:00:00": -74400000.0,
                "2021-03-31 00:00:00": null
            },
            "Financing Cash Flow": {
                "2025-03-31 00:00:00": 5300000.0,
                "2024-03-31 00:00:00": 1156400000.0,
                "2023-03-31 00:00:00": 20077000.0,
                "2022-03-31 00:00:00": -4612300000.0,
                "2021-03-31 00:00:00": null
            },
            "Net Other Financing Charges": {
                "2025-03-31 00:00:00": 994500000.0,
                "2024-03-31 00:00:00": 5678600000.0,
                "2023-03-31 00:00:00": -21228000.0,
                "2022-03-31 00:00:00": -353000000.0,
                "2021-03-31 00:00:00": null
            },
            "Interest Paid Cff": {
                "2025-03-31 00:00:00": -98100000.0,
                "2024-03-31 00:00:00": -325800000.0,
                "2023-03-31 00:00:00": -308483000.0,
                "2022-03-31 00:00:00": -261000000.0,
                "2021-03-31 00:00:00": null
            },
            "Cash Dividends Paid": {
                "2025-03-31 00:00:00": -249600000.0,
                "2024-03-31 00:00:00": -162000000.0,
                "2023-03-31 00:00:00": -35411000.0,
                "2022-03-31 00:00:00": -29500000.0,
                "2021-03-31 00:00:00": null
            },
            "Common Stock Dividend Paid": {
                "2025-03-31 00:00:00": null,
                "2024-03-31 00:00:00": -162100000.0,
                "2023-03-31 00:00:00": -35400000.0,
                "2022-03-31 00:00:00": -29500000.0,
                "2021-03-31 00:00:00": null
            },
            "Net Common Stock Issuance": {
                "2025-03-31 00:00:00": 2700000.0,
                "2024-03-31 00:00:00": 35600000.0,
                "2023-03-31 00:00:00": 425610000.0,
                "2022-03-31 00:00:00": 1236700000.0,
                "2021-03-31 00:00:00": null
            },
            "Common Stock Issuance": {
                "2025-03-31 00:00:00": 2700000.0,
                "2024-03-31 00:00:00": 35600000.0,
                "2023-03-31 00:00:00": 425610000.0,
                "2022-03-31 00:00:00": 1236700000.0,
                "2021-03-31 00:00:00": null
            },
            "Net Issuance Payments Of Debt": {
                "2025-03-31 00:00:00": -781800000.0,
                "2024-03-31 00:00:00": -4070000000.0,
                "2023-03-31 00:00:00": -40411000.0,
                "2022-03-31 00:00:00": -5205500000.0,
                "2021-03-31 00:00:00": null
            },
            "Net Short Term Debt Issuance": {
                "2025-03-31 00:00:00": null,
                "2024-03-31 00:00:00": null,
                "2023-03-31 00:00:00": -308200000.0,
                "2022-03-31 00:00:00": -197900000.0,
                "2021-03-31 00:00:00": -475389000.0
            },
            "Net Long Term Debt Issuance": {
                "2025-03-31 00:00:00": -781800000.0,
                "2024-03-31 00:00:00": -4070000000.0,
                "2023-03-31 00:00:00": -40411000.0,
                "2022-03-31 00:00:00": -5007600000.0,
                "2021-03-31 00:00:00": null
            },
            "Investing Cash Flow": {
                "2025-03-31 00:00:00": -721300000.0,
                "2024-03-31 00:00:00": 1808300000.0,
                "2023-03-31 00:00:00": -202548000.0,
                "2022-03-31 00:00:00": 305100000.0,
                "2021-03-31 00:00:00": null
            },
            "Net Other Investing Changes": {
                "2025-03-31 00:00:00": null,
                "2024-03-31 00:00:00": 187714000.0,
                "2023-03-31 00:00:00": -236114000.0,
                "2022-03-31 00:00:00": null,
                "2021-03-31 00:00:00": -100000.0
            },
            "Interest Received Cfi": {
                "2025-03-31 00:00:00": 354600000.0,
                "2024-03-31 00:00:00": 332200000.0,
                "2023-03-31 00:00:00": 415285000.0,
                "2022-03-31 00:00:00": 361500000.0,
                "2021-03-31 00:00:00": null
            },
            "Net Investment Purchase And Sale": {
                "2025-03-31 00:00:00": -87400000.0,
                "2024-03-31 00:00:00": 1771900000.0,
                "2023-03-31 00:00:00": -90000.0,
                "2022-03-31 00:00:00": -377100000.0,
                "2021-03-31 00:00:00": null
            },
            "Net Investment Properties Purchase And Sale": {
                "2025-03-31 00:00:00": -221300000.0,
                "2024-03-31 00:00:00": -2600000.0,
                "2023-03-31 00:00:00": -659000.0,
                "2022-03-31 00:00:00": -3900000.0,
                "2021-03-31 00:00:00": null
            },
            "Sale Of Investment Properties": {
                "2025-03-31 00:00:00": null,
                "2024-03-31 00:00:00": null,
                "2023-03-31 00:00:00": null,
                "2022-03-31 00:00:00": 0.0,
                "2021-03-31 00:00:00": 26763000.0
            },
            "Purchase Of Investment Properties": {
                "2025-03-31 00:00:00": -221300000.0,
                "2024-03-31 00:00:00": -2600000.0,
                "2023-03-31 00:00:00": -659000.0,
                "2022-03-31 00:00:00": -3900000.0,
                "2021-03-31 00:00:00": null
            },
            "Net Intangibles Purchase And Sale": {
                "2025-03-31 00:00:00": null,
                "2024-03-31 00:00:00": 0.0,
                "2023-03-31 00:00:00": 0.0,
                "2022-03-31 00:00:00": 0.0,
                "2021-03-31 00:00:00": 544000.0
            },
            "Purchase Of Intangibles": {
                "2025-03-31 00:00:00": null,
                "2024-03-31 00:00:00": 0.0,
                "2023-03-31 00:00:00": 0.0,
                "2022-03-31 00:00:00": null,
                "2021-03-31 00:00:00": null
            },
            "Net PPE Purchase And Sale": {
                "2025-03-31 00:00:00": -767200000.0,
                "2024-03-31 00:00:00": -293200000.0,
                "2023-03-31 00:00:00": -380970000.0,
                "2022-03-31 00:00:00": 425900000.0,
                "2021-03-31 00:00:00": null
            },
            "Sale Of PPE": {
                "2025-03-31 00:00:00": 2900000.0,
                "2024-03-31 00:00:00": 146400000.0,
                "2023-03-31 00:00:00": 37084000.0,
                "2022-03-31 00:00:00": 436600000.0,
                "2021-03-31 00:00:00": null
            },
            "Purchase Of PPE": {
                "2025-03-31 00:00:00": -770100000.0,
                "2024-03-31 00:00:00": -439600000.0,
                "2023-03-31 00:00:00": -418054000.0,
                "2022-03-31 00:00:00": -10700000.0,
                "2021-03-31 00:00:00": null
            },
            "Operating Cash Flow": {
                "2025-03-31 00:00:00": 966100000.0,
                "2024-03-31 00:00:00": -255200000.0,
                "2023-03-31 00:00:00": 328797000.0,
                "2022-03-31 00:00:00": 4232800000.0,
                "2021-03-31 00:00:00": null
            },
            "Taxes Refund Paid": {
                "2025-03-31 00:00:00": -689900000.0,
                "2024-03-31 00:00:00": -540100000.0,
                "2023-03-31 00:00:00": -523018000.0,
                "2022-03-31 00:00:00": -230500000.0,
                "2021-03-31 00:00:00": null
            },
            "Change In Working Capital": {
                "2025-03-31 00:00:00": -3300100000.0,
                "2024-03-31 00:00:00": -3068400000.0,
                "2023-03-31 00:00:00": -1159079000.0,
                "2022-03-31 00:00:00": 3641100000.0,
                "2021-03-31 00:00:00": null
            },
            "Change In Other Current Liabilities": {
                "2025-03-31 00:00:00": -958900000.0,
                "2024-03-31 00:00:00": 1002100000.0,
                "2023-03-31 00:00:00": -2445152000.0,
                "2022-03-31 00:00:00": 1425200000.0,
                "2021-03-31 00:00:00": null
            },
            "Change In Other Current Assets": {
                "2025-03-31 00:00:00": -4275800000.0,
                "2024-03-31 00:00:00": -1095300000.0,
                "2023-03-31 00:00:00": 1376734000.0,
                "2022-03-31 00:00:00": -1354400000.0,
                "2021-03-31 00:00:00": null
            },
            "Change In Payable": {
                "2025-03-31 00:00:00": 8800000.0,
                "2024-03-31 00:00:00": 55600000.0,
                "2023-03-31 00:00:00": 76655000.0,
                "2022-03-31 00:00:00": -9600000.0,
                "2021-03-31 00:00:00": null
            },
            "Change In Inventory": {
                "2025-03-31 00:00:00": 2645900000.0,
                "2024-03-31 00:00:00": -2191300000.0,
                "2023-03-31 00:00:00": -618065000.0,
                "2022-03-31 00:00:00": 3217200000.0,
                "2021-03-31 00:00:00": null
            },
            "Change In Receivables": {
                "2025-03-31 00:00:00": -1011200000.0,
                "2024-03-31 00:00:00": -777900000.0,
                "2023-03-31 00:00:00": 140961000.0,
                "2022-03-31 00:00:00": 208200000.0,
                "2021-03-31 00:00:00": null
            },
            "Other Non Cash Items": {
                "2025-03-31 00:00:00": -296500000.0,
                "2024-03-31 00:00:00": -26100000.0,
                "2023-03-31 00:00:00": -106802000.0,
                "2022-03-31 00:00:00": -124200000.0,
                "2021-03-31 00:00:00": null
            },
            "Deferred Tax": {
                "2025-03-31 00:00:00": null,
                "2024-03-31 00:00:00": 1510000.0,
                "2023-03-31 00:00:00": -2014000.0,
                "2022-03-31 00:00:00": null,
                "2021-03-31 00:00:00": null
            },
            "Depreciation And Amortization": {
                "2025-03-31 00:00:00": 304600000.0,
                "2024-03-31 00:00:00": 180600000.0,
                "2023-03-31 00:00:00": 165085000.0,
                "2022-03-31 00:00:00": 166700000.0,
                "2021-03-31 00:00:00": null
            },
            "Depreciation": {
                "2025-03-31 00:00:00": 304600000.0,
                "2024-03-31 00:00:00": 180600000.0,
                "2023-03-31 00:00:00": 165085000.0,
                "2022-03-31 00:00:00": 166700000.0,
                "2021-03-31 00:00:00": null
            },
            "Pension And Employee Benefit Expense": {
                "2025-03-31 00:00:00": null,
                "2024-03-31 00:00:00": -5570000.0,
                "2023-03-31 00:00:00": 6142000.0,
                "2022-03-31 00:00:00": 3700000.0,
                "2021-03-31 00:00:00": 3013000.0
            },
            "Gain Loss On Investment Securities": {
                "2025-03-31 00:00:00": null,
                "2024-03-31 00:00:00": -900000.0,
                "2023-03-31 00:00:00": null,
                "2022-03-31 00:00:00": null,
                "2021-03-31 00:00:00": null
            },
            "Gain Loss On Sale Of Business": {
                "2025-03-31 00:00:00": null,
                "2024-03-31 00:00:00": -887000.0,
                "2023-03-31 00:00:00": -85699000.0,
                "2022-03-31 00:00:00": -3400000.0,
                "2021-03-31 00:00:00": 0.0
            },
            "Net Income From Continuing Operations": {
                "2025-03-31 00:00:00": 4905300000.0,
                "2024-03-31 00:00:00": 3185800000.0,
                "2023-03-31 00:00:00": 1967071000.0,
                "2022-03-31 00:00:00": 715200000.0,
                "2021-03-31 00:00:00": null
            }
        }
    },
    "sentiment_analysis": {
        "newsapi": {
            "positive": 0,
            "negative": 0,
            "neutral": 0
        },
        "gnews": {
            "positive": 0,
            "negative": 0,
            "neutral": 0
        },
        "reddit": {
            "positive": 0,
            "negative": 0,
            "neutral": 0
        },
        "google_news": {
            "positive": 1,
            "negative": 2,
            "neutral": 1
        },
        "aggregated": {
            "positive": 1,
            "negative": 2,
            "neutral": 1
        }
    },
    "mpt_metrics": {
        "annual_return": 0.7019192050148139,
        "annual_volatility": 0.511269202093058,
        "sharpe_ratio": 1.2555405300904,
        "beta": 1.664794053931443,
        "alpha": 0.5280558466977767
    },
    "institutional_holders": {
        "institutional_ownership_pct": 0.67079,
        "insider_ownership_pct": 0.13143
    },
    "mutual_fund_holders": {},
    "support_level": 526.0222299499511,
    "resistance_level": 610.6274871826172,
    "risk_level": "MEDIUM",
    "timeframe": "SHORT_TERM",
    "explanation": "Recommendation for ANANT RAJ LIMITED (ANANTRAJ.NS): STRONG SELL\nCurrent Price: 581.55\n\nBuy Score: -0.370, Sell Score: 0.470\n\nBearish Factors:\n- Stock is in a downtrend (50-day SMA < 200-day SMA).\n- Negative market sentiment from news and social media.\n- Negative risk-adjusted return (Sharpe Ratio).\n\nRisk Assessment:\n- Volatility: 0.0225 (higher values indicate higher risk)\n- Sector: Real Estate\n- Industry: Real Estate - Development\n",
    "ml_analysis": {
        "success": true,
        "predicted_price": 526.0401832364438,
        "confidence": -4.920480628780169,
        "mse": 104044.59719881856,
        "mae": 273.38520054598405,
        "r2_score": -4.920480628780169,
        "stacking_regressor_metrics": {
            "mse": 104044.59719881856,
            "mae": 273.38520054598405,
            "r2": -4.920480628780169
        },
        "lstm_metrics": {
            "mse": 0.007011997047811747,
            "r2": 0.6108490228652954,
            "adv_mse": 0.06267254799604416,
            "adv_r2": -2.478193521499634
        },
        "transformer_metrics": {
            "mse": 0.026658520102500916,
            "r2": -0.47949135303497314,
            "adv_mse": 0.07232572883367538,
            "adv_r2": -3.0139245986938477
        },
        "rl_metrics": {
            "success": true,
            "recommendation": "HOLD",
            "performance_pct": -2.692784777641486,
            "final_net_worth": 97307.21522235851,
            "average_reward": 10056985.969774405,
            "average_events_per_episode": 149.24,
            "actions_distribution": {
                "hold": 0.9202702702702703,
                "buy": 0.03783783783783784,
                "sell": 0.041891891891891894
            },
            "epoch_logs": [
                {
                    "episode": 10,
                    "total_reward": 11027114.392218044,
                    "average_reward": 8584602.391754508,
                    "events_triggered": 170
                },
                {
                    "episode": 20,
                    "total_reward": 12860009.299228553,
                    "average_reward": 9879125.194509903,
                    "events_triggered": 151
                },
                {
                    "episode": 30,
                    "total_reward": 7183265.736731887,
                    "average_reward": 10612720.391975284,
                    "events_triggered": 141
                },
                {
                    "episode": 40,
                    "total_reward": 12548865.256254386,
                    "average_reward": 11100117.318646846,
                    "events_triggered": 139
                },
                {
                    "episode": 50,
                    "total_reward": 8496739.022598196,
                    "average_reward": 10996123.924282975,
                    "events_triggered": 146
                },
                {
                    "episode": 60,
                    "total_reward": 14000749.921706831,
                    "average_reward": 10331359.506605007,
                    "events_triggered": 159
                },
                {
                    "episode": 70,
                    "total_reward": 5236259.034493472,
                    "average_reward": 10686987.06857129,
                    "events_triggered": 134
                },
                {
                    "episode": 80,
                    "total_reward": 6617780.526664858,
                    "average_reward": 8286784.168849105,
                    "events_triggered": 147
                },
                {
                    "episode": 90,
                    "total_reward": 6667663.726984691,
                    "average_reward": 8819626.626529912,
                    "events_triggered": 156
                },
                {
                    "episode": 100,
                    "total_reward": 8189937.086991368,
                    "average_reward": 11272413.106019214,
                    "events_triggered": 160
                }
            ]
        },
        "ensemble_components": {
            "stacking_regressor": 487.6475272483937,
            "lstm": 552.510009765625,
            "transformer": 537.9630126953125
        }
    },
    "timestamp": "2025-07-25 11:32:08"
}