{
    "success": true,
    "stock_data": {
        "symbol": "BEL.NS",
        "name": "BHARAT ELECTRONICS LTD",
        "current_price": {
            "INR": 389.5,
            "USD": 4.44,
            "EUR": 3.84,
            "BTC": 3.891e-05,
            "ETH": 0.00122267
        },
        "sector": "Industrials",
        "industry": "Aerospace & Defense",
        "pe_ratio": 51.657825,
        "dividends": 0.96
    },
    "recommendation": "NEUTRAL",
    "buy_score": 0.0,
    "sell_score": 0.0,
    "technical_indicators": {
        "sma_50": 401.78200073242186,
        "sma_200": 319.6191618347168,
        "ema_50": 389.7684596880029,
        "rsi": 44.467813418988364,
        "macd": -5.008554216415803,
        "signal_line": -3.437034264875618,
        "macd_histogram": -1.5715199515401848,
        "bb_upper": 416.6518138840004,
        "bb_lower": 376.43318977810895,
        "volatility": 0.013237531456681089,
        "momentum": -0.05023166495226987,
        "volume_trend": "HIGH"
    },
    "fundamental_analysis": {
        "market_cap": 2847159353344,
        "pe_ratio": 51.657825,
        "dividend_yield": 96.0,
        "52w_high": 436.0,
        "52w_low": 240.25,
        "balance_sheet": {
            "Treasury Shares Number": {
                "2025-03-31 00:00:00": null,
                "2024-03-31 00:00:00": 0.0,
                "2023-03-31 00:00:00": null,
                "2022-03-31 00:00:00": null,
                "2021-03-31 00:00:00": null
            },
            "Ordinary Shares Number": {
                "2025-03-31 00:00:00": 7309778829.0,
                "2024-03-31 00:00:00": 7309778829.0,
                "2023-03-31 00:00:00": 7309778829.0,
                "2022-03-31 00:00:00": 7309778829.0,
                "2021-03-31 00:00:00": null
            },
            "Share Issued": {
                "2025-03-31 00:00:00": 7309778829.0,
                "2024-03-31 00:00:00": 7309778829.0,
                "2023-03-31 00:00:00": 7309778829.0,
                "2022-03-31 00:00:00": 7309778829.0,
                "2021-03-31 00:00:00": null
            },
            "Total Debt": {
                "2025-03-31 00:00:00": 612300000.0,
                "2024-03-31 00:00:00": 625100000.0,
                "2023-03-31 00:00:00": 613400000.0,
                "2022-03-31 00:00:00": 527000000.0,
                "2021-03-31 00:00:00": null
            },
            "Tangible Book Value": {
                "2025-03-31 00:00:00": 191844100000.0,
                "2024-03-31 00:00:00": 156424700000.0,
                "2023-03-31 00:00:00": 130994300000.0,
                "2022-03-31 00:00:00": 115600000000.0,
                "2021-03-31 00:00:00": null
            },
            "Invested Capital": {
                "2025-03-31 00:00:00": 199738900000.0,
                "2024-03-31 00:00:00": 163264700000.0,
                "2023-03-31 00:00:00": 138616300000.0,
                "2022-03-31 00:00:00": 122859300000.0,
                "2021-03-31 00:00:00": null
            },
            "Working Capital": {
                "2025-03-31 00:00:00": 151053400000.0,
                "2024-03-31 00:00:00": 120362500000.0,
                "2023-03-31 00:00:00": 94819600000.0,
                "2022-03-31 00:00:00": 77126700000.0,
                "2021-03-31 00:00:00": null
            },
            "Net Tangible Assets": {
                "2025-03-31 00:00:00": 191844100000.0,
                "2024-03-31 00:00:00": 156424700000.0,
                "2023-03-31 00:00:00": 130994300000.0,
                "2022-03-31 00:00:00": 115600000000.0,
                "2021-03-31 00:00:00": null
            },
            "Capital Lease Obligations": {
                "2025-03-31 00:00:00": 612300000.0,
                "2024-03-31 00:00:00": 625100000.0,
                "2023-03-31 00:00:00": 613400000.0,
                "2022-03-31 00:00:00": 527000000.0,
                "2021-03-31 00:00:00": null
            },
            "Common Stock Equity": {
                "2025-03-31 00:00:00": 199738900000.0,
                "2024-03-31 00:00:00": 163264700000.0,
                "2023-03-31 00:00:00": 138616300000.0,
                "2022-03-31 00:00:00": 122859300000.0,
                "2021-03-31 00:00:00": null
            },
            "Total Capitalization": {
                "2025-03-31 00:00:00": 199738900000.0,
                "2024-03-31 00:00:00": 163264700000.0,
                "2023-03-31 00:00:00": 138616300000.0,
                "2022-03-31 00:00:00": 122859300000.0,
                "2021-03-31 00:00:00": null
            },
            "Total Equity Gross Minority Interest": {
                "2025-03-31 00:00:00": 199928300000.0,
                "2024-03-31 00:00:00": 163443900000.0,
                "2023-03-31 00:00:00": 138793800000.0,
                "2022-03-31 00:00:00": 123022700000.0,
                "2021-03-31 00:00:00": null
            },
            "Minority Interest": {
                "2025-03-31 00:00:00": 189400000.0,
                "2024-03-31 00:00:00": 179200000.0,
                "2023-03-31 00:00:00": 177500000.0,
                "2022-03-31 00:00:00": 163400000.0,
                "2021-03-31 00:00:00": null
            },
            "Stockholders Equity": {
                "2025-03-31 00:00:00": 199738900000.0,
                "2024-03-31 00:00:00": 163264700000.0,
                "2023-03-31 00:00:00": 138616300000.0,
                "2022-03-31 00:00:00": 122859300000.0,
                "2021-03-31 00:00:00": null
            },
            "Other Equity Interest": {
                "2025-03-31 00:00:00": 192429100000.0,
                "2024-03-31 00:00:00": 155954900000.0,
                "2023-03-31 00:00:00": 131306500000.0,
                "2022-03-31 00:00:00": 120422700000.0,
                "2021-03-31 00:00:00": null
            },
            "Retained Earnings": {
                "2025-03-31 00:00:00": null,
                "2024-03-31 00:00:00": 114743500000.0,
                "2023-03-31 00:00:00": 93517900000.0,
                "2022-03-31 00:00:00": 80100700000.0,
                "2021-03-31 00:00:00": 70345500000.0
            },
            "Additional Paid In Capital": {
                "2025-03-31 00:00:00": null,
                "2024-03-31 00:00:00": 186800000.0,
                "2023-03-31 00:00:00": 186800000.0,
                "2022-03-31 00:00:00": 186800000.0,
                "2021-03-31 00:00:00": 186800000.0
            },
            "Capital Stock": {
                "2025-03-31 00:00:00": 7309800000.0,
                "2024-03-31 00:00:00": 7309800000.0,
                "2023-03-31 00:00:00": 7309800000.0,
                "2022-03-31 00:00:00": 2436600000.0,
                "2021-03-31 00:00:00": null
            },
            "Common Stock": {
                "2025-03-31 00:00:00": 7309800000.0,
                "2024-03-31 00:00:00": 7309800000.0,
                "2023-03-31 00:00:00": 7309800000.0,
                "2022-03-31 00:00:00": 2436600000.0,
                "2021-03-31 00:00:00": null
            },
            "Total Liabilities Net Minority Interest": {
                "2025-03-31 00:00:00": 208390300000.0,
                "2024-03-31 00:00:00": 231822900000.0,
                "2023-03-31 00:00:00": 216117900000.0,
                "2022-03-31 00:00:00": 216083100000.0,
                "2021-03-31 00:00:00": null
            },
            "Total Non Current Liabilities Net Minority Interest": {
                "2025-03-31 00:00:00": 10864900000.0,
                "2024-03-31 00:00:00": 11555600000.0,
                "2023-03-31 00:00:00": 10460100000.0,
                "2022-03-31 00:00:00": 20272700000.0,
                "2021-03-31 00:00:00": null
            },
            "Tradeand Other Payables Non Current": {
                "2025-03-31 00:00:00": null,
                "2024-03-31 00:00:00": null,
                "2023-03-31 00:00:00": 3700000.0,
                "2022-03-31 00:00:00": 3400000.0,
                "2021-03-31 00:00:00": 2900000.0
            },
            "Non Current Deferred Revenue": {
                "2025-03-31 00:00:00": 1015500000.0,
                "2024-03-31 00:00:00": 1177600000.0,
                "2023-03-31 00:00:00": 1339500000.0,
                "2022-03-31 00:00:00": 1484300000.0,
                "2021-03-31 00:00:00": null
            },
            "Non Current Deferred Taxes Liabilities": {
                "2025-03-31 00:00:00": 95200000.0,
                "2024-03-31 00:00:00": 54700000.0,
                "2023-03-31 00:00:00": 28900000.0,
                "2022-03-31 00:00:00": 14500000.0,
                "2021-03-31 00:00:00": null
            },
            "Long Term Debt And Capital Lease Obligation": {
                "2025-03-31 00:00:00": 586900000.0,
                "2024-03-31 00:00:00": 602500000.0,
                "2023-03-31 00:00:00": 594200000.0,
                "2022-03-31 00:00:00": 515100000.0,
                "2021-03-31 00:00:00": null
            },
            "Long Term Capital Lease Obligation": {
                "2025-03-31 00:00:00": 586900000.0,
                "2024-03-31 00:00:00": 602500000.0,
                "2023-03-31 00:00:00": 594200000.0,
                "2022-03-31 00:00:00": 515100000.0,
                "2021-03-31 00:00:00": null
            },
            "Long Term Debt": {
                "2025-03-31 00:00:00": 0.0,
                "2024-03-31 00:00:00": 0.0,
                "2023-03-31 00:00:00": 0.0,
                "2022-03-31 00:00:00": 0.0,
                "2021-03-31 00:00:00": null
            },
            "Long Term Provisions": {
                "2025-03-31 00:00:00": 9021600000.0,
                "2024-03-31 00:00:00": 9672800000.0,
                "2023-03-31 00:00:00": 8446500000.0,
                "2022-03-31 00:00:00": 18053200000.0,
                "2021-03-31 00:00:00": null
            },
            "Current Liabilities": {
                "2025-03-31 00:00:00": 197525400000.0,
                "2024-03-31 00:00:00": 220267300000.0,
                "2023-03-31 00:00:00": 205657800000.0,
                "2022-03-31 00:00:00": 195810400000.0,
                "2021-03-31 00:00:00": null
            },
            "Other Current Liabilities": {
                "2025-03-31 00:00:00": 142870200000.0,
                "2024-03-31 00:00:00": 2742400000.0,
                "2023-03-31 00:00:00": 3293600000.0,
                "2022-03-31 00:00:00": 2296900000.0,
                "2021-03-31 00:00:00": null
            },
            "Current Deferred Taxes Liabilities": {
                "2025-03-31 00:00:00": null,
                "2024-03-31 00:00:00": 2800000.0,
                "2023-03-31 00:00:00": 0.0,
                "2022-03-31 00:00:00": 6900000.0,
                "2021-03-31 00:00:00": 0.0
            },
            "Current Debt And Capital Lease Obligation": {
                "2025-03-31 00:00:00": 25400000.0,
                "2024-03-31 00:00:00": 22600000.0,
                "2023-03-31 00:00:00": 19200000.0,
                "2022-03-31 00:00:00": 11900000.0,
                "2021-03-31 00:00:00": null
            },
            "Current Capital Lease Obligation": {
                "2025-03-31 00:00:00": 25400000.0,
                "2024-03-31 00:00:00": 22600000.0,
                "2023-03-31 00:00:00": 19200000.0,
                "2022-03-31 00:00:00": 11900000.0,
                "2021-03-31 00:00:00": null
            },
            "Current Debt": {
                "2025-03-31 00:00:00": 0.0,
                "2024-03-31 00:00:00": 0.0,
                "2023-03-31 00:00:00": 0.0,
                "2022-03-31 00:00:00": 0.0,
                "2021-03-31 00:00:00": null
            },
            "Current Provisions": {
                "2025-03-31 00:00:00": 7397100000.0,
                "2024-03-31 00:00:00": 6945300000.0,
                "2023-03-31 00:00:00": 6275400000.0,
                "2022-03-31 00:00:00": 4238200000.0,
                "2021-03-31 00:00:00": null
            },
            "Payables": {
                "2025-03-31 00:00:00": 33387700000.0,
                "2024-03-31 00:00:00": 46610300000.0,
                "2023-03-31 00:00:00": 42122300000.0,
                "2022-03-31 00:00:00": 40332600000.0,
                "2021-03-31 00:00:00": null
            },
            "Other Payable": {
                "2025-03-31 00:00:00": null,
                "2024-03-31 00:00:00": 9518400000.0,
                "2023-03-31 00:00:00": 8793900000.0,
                "2022-03-31 00:00:00": 6611200000.0,
                "2021-03-31 00:00:00": 6787100000.0
            },
            "Dividends Payable": {
                "2025-03-31 00:00:00": null,
                "2024-03-31 00:00:00": 28800000.0,
                "2023-03-31 00:00:00": 24600000.0,
                "2022-03-31 00:00:00": 21500000.0,
                "2021-03-31 00:00:00": 21100000.0
            },
            "Total Tax Payable": {
                "2025-03-31 00:00:00": 0.0,
                "2024-03-31 00:00:00": 2800000.0,
                "2023-03-31 00:00:00": 0.0,
                "2022-03-31 00:00:00": 6900000.0,
                "2021-03-31 00:00:00": null
            },
            "Accounts Payable": {
                "2025-03-31 00:00:00": 33387700000.0,
                "2024-03-31 00:00:00": 37063100000.0,
                "2023-03-31 00:00:00": 33303800000.0,
                "2022-03-31 00:00:00": 33693000000.0,
                "2021-03-31 00:00:00": null
            },
            "Total Assets": {
                "2025-03-31 00:00:00": 408318600000.0,
                "2024-03-31 00:00:00": 395266800000.0,
                "2023-03-31 00:00:00": 354911700000.0,
                "2022-03-31 00:00:00": 339105800000.0,
                "2021-03-31 00:00:00": null
            },
            "Total Non Current Assets": {
                "2025-03-31 00:00:00": 59739800000.0,
                "2024-03-31 00:00:00": 54637000000.0,
                "2023-03-31 00:00:00": 54434300000.0,
                "2022-03-31 00:00:00": 66168700000.0,
                "2021-03-31 00:00:00": null
            },
            "Other Non Current Assets": {
                "2025-03-31 00:00:00": 1943600000.0,
                "2024-03-31 00:00:00": 2520000000.0,
                "2023-03-31 00:00:00": 58700000.0,
                "2022-03-31 00:00:00": 281400000.0,
                "2021-03-31 00:00:00": null
            },
            "Non Current Prepaid Assets": {
                "2025-03-31 00:00:00": null,
                "2024-03-31 00:00:00": 144600000.0,
                "2023-03-31 00:00:00": 214100000.0,
                "2022-03-31 00:00:00": 275800000.0,
                "2021-03-31 00:00:00": 283000000.0
            },
            "Non Current Deferred Taxes Assets": {
                "2025-03-31 00:00:00": 5348400000.0,
                "2024-03-31 00:00:00": 5746800000.0,
                "2023-03-31 00:00:00": 5037200000.0,
                "2022-03-31 00:00:00": 6209400000.0,
                "2021-03-31 00:00:00": null
            },
            "Investmentin Financial Assets": {
                "2025-03-31 00:00:00": 6057600000.0,
                "2024-03-31 00:00:00": 5306600000.0,
                "2023-03-31 00:00:00": 4492600000.0,
                "2022-03-31 00:00:00": 13391000000.0,
                "2021-03-31 00:00:00": null
            },
            "Available For Sale Securities": {
                "2025-03-31 00:00:00": 6057600000.0,
                "2024-03-31 00:00:00": 1700000.0,
                "2023-03-31 00:00:00": 1600000.0,
                "2022-03-31 00:00:00": 1400000.0,
                "2021-03-31 00:00:00": null
            },
            "Financial Assets Designatedas Fair Value Through Profitor Loss Total": {
                "2025-03-31 00:00:00": null,
                "2024-03-31 00:00:00": 5304900000.0,
                "2023-03-31 00:00:00": 4491000000.0,
                "2022-03-31 00:00:00": 13389600000.0,
                "2021-03-31 00:00:00": 11159200000.0
            },
            "Long Term Equity Investment": {
                "2025-03-31 00:00:00": 1613600000.0,
                "2024-03-31 00:00:00": 1515700000.0,
                "2023-03-31 00:00:00": 2007300000.0,
                "2022-03-31 00:00:00": 2329200000.0,
                "2021-03-31 00:00:00": null
            },
            "Investmentsin Associatesat Cost": {
                "2025-03-31 00:00:00": 1613600000.0,
                "2024-03-31 00:00:00": 1515700000.0,
                "2023-03-31 00:00:00": 2007300000.0,
                "2022-03-31 00:00:00": 2329200000.0,
                "2021-03-31 00:00:00": null
            },
            "Investment Properties": {
                "2025-03-31 00:00:00": 400000.0,
                "2024-03-31 00:00:00": 400000.0,
                "2023-03-31 00:00:00": 600000.0,
                "2022-03-31 00:00:00": 700000.0,
                "2021-03-31 00:00:00": null
            },
            "Goodwill And Other Intangible Assets": {
                "2025-03-31 00:00:00": 7894800000.0,
                "2024-03-31 00:00:00": 6840000000.0,
                "2023-03-31 00:00:00": 7622000000.0,
                "2022-03-31 00:00:00": 7259300000.0,
                "2021-03-31 00:00:00": null
            },
            "Other Intangible Assets": {
                "2025-03-31 00:00:00": 7894800000.0,
                "2024-03-31 00:00:00": 6840000000.0,
                "2023-03-31 00:00:00": 7622000000.0,
                "2022-03-31 00:00:00": 7259300000.0,
                "2021-03-31 00:00:00": null
            },
            "Net PPE": {
                "2025-03-31 00:00:00": 36815100000.0,
                "2024-03-31 00:00:00": 32755000000.0,
                "2023-03-31 00:00:00": 30783600000.0,
                "2022-03-31 00:00:00": 29855500000.0,
                "2021-03-31 00:00:00": null
            },
            "Accumulated Depreciation": {
                "2025-03-31 00:00:00": null,
                "2024-03-31 00:00:00": -28109800000.0,
                "2023-03-31 00:00:00": -24306700000.0,
                "2022-03-31 00:00:00": -20412500000.0,
                "2021-03-31 00:00:00": -16747100000.0
            },
            "Gross PPE": {
                "2025-03-31 00:00:00": 36815100000.0,
                "2024-03-31 00:00:00": 60864800000.0,
                "2023-03-31 00:00:00": 55090300000.0,
                "2022-03-31 00:00:00": 50268000000.0,
                "2021-03-31 00:00:00": null
            },
            "Construction In Progress": {
                "2025-03-31 00:00:00": 4769800000.0,
                "2024-03-31 00:00:00": 4882700000.0,
                "2023-03-31 00:00:00": 3852900000.0,
                "2022-03-31 00:00:00": 4774200000.0,
                "2021-03-31 00:00:00": null
            },
            "Other Properties": {
                "2025-03-31 00:00:00": 32045300000.0,
                "2024-03-31 00:00:00": 15940300000.0,
                "2023-03-31 00:00:00": 14034700000.0,
                "2022-03-31 00:00:00": 12734300000.0,
                "2021-03-31 00:00:00": null
            },
            "Machinery Furniture Equipment": {
                "2025-03-31 00:00:00": null,
                "2024-03-31 00:00:00": 25336900000.0,
                "2023-03-31 00:00:00": 23448200000.0,
                "2022-03-31 00:00:00": 20140800000.0,
                "2021-03-31 00:00:00": 18384800000.0
            },
            "Buildings And Improvements": {
                "2025-03-31 00:00:00": null,
                "2024-03-31 00:00:00": 10830800000.0,
                "2023-03-31 00:00:00": 9926500000.0,
                "2022-03-31 00:00:00": 8854400000.0,
                "2021-03-31 00:00:00": 8282600000.0
            },
            "Land And Improvements": {
                "2025-03-31 00:00:00": null,
                "2024-03-31 00:00:00": 3874100000.0,
                "2023-03-31 00:00:00": 3828000000.0,
                "2022-03-31 00:00:00": 3764300000.0,
                "2021-03-31 00:00:00": 3676600000.0
            },
            "Properties": {
                "2025-03-31 00:00:00": null,
                "2024-03-31 00:00:00": 0.0,
                "2023-03-31 00:00:00": 0.0,
                "2022-03-31 00:00:00": 0.0,
                "2021-03-31 00:00:00": 0.0
            },
            "Current Assets": {
                "2025-03-31 00:00:00": 348578800000.0,
                "2024-03-31 00:00:00": 340629800000.0,
                "2023-03-31 00:00:00": 300477400000.0,
                "2022-03-31 00:00:00": 272937100000.0,
                "2021-03-31 00:00:00": null
            },
            "Other Current Assets": {
                "2025-03-31 00:00:00": 64810100000.0,
                "2024-03-31 00:00:00": 78800000.0,
                "2023-03-31 00:00:00": 306100000.0,
                "2022-03-31 00:00:00": 122400000.0,
                "2021-03-31 00:00:00": null
            },
            "Restricted Cash": {
                "2025-03-31 00:00:00": null,
                "2024-03-31 00:00:00": 241000000.0,
                "2023-03-31 00:00:00": 197300000.0,
                "2022-03-31 00:00:00": 171000000.0,
                "2021-03-31 00:00:00": 125600000.0
            },
            "Prepaid Assets": {
                "2025-03-31 00:00:00": null,
                "2024-03-31 00:00:00": 22099300000.0,
                "2023-03-31 00:00:00": 19128400000.0,
                "2022-03-31 00:00:00": 20715500000.0,
                "2021-03-31 00:00:00": 22276300000.0
            },
            "Inventory": {
                "2025-03-31 00:00:00": 91189800000.0,
                "2024-03-31 00:00:00": 74468900000.0,
                "2023-03-31 00:00:00": 64480400000.0,
                "2022-03-31 00:00:00": 55919000000.0,
                "2021-03-31 00:00:00": null
            },
            "Inventories Adjustments Allowances": {
                "2025-03-31 00:00:00": null,
                "2024-03-31 00:00:00": -32700000.0,
                "2023-03-31 00:00:00": -17100000.0,
                "2022-03-31 00:00:00": -30100000.0,
                "2021-03-31 00:00:00": -23000000.0
            },
            "Other Inventories": {
                "2025-03-31 00:00:00": null,
                "2024-03-31 00:00:00": 140700000.0,
                "2023-03-31 00:00:00": 146700000.0,
                "2022-03-31 00:00:00": 105000000.0,
                "2021-03-31 00:00:00": 107000000.0
            },
            "Finished Goods": {
                "2025-03-31 00:00:00": null,
                "2024-03-31 00:00:00": 2604900000.0,
                "2023-03-31 00:00:00": 3823200000.0,
                "2022-03-31 00:00:00": 2590000000.0,
                "2021-03-31 00:00:00": 3372800000.0
            },
            "Work In Process": {
                "2025-03-31 00:00:00": null,
                "2024-03-31 00:00:00": 26515000000.0,
                "2023-03-31 00:00:00": 19628700000.0,
                "2022-03-31 00:00:00": 17016300000.0,
                "2021-03-31 00:00:00": 13855000000.0
            },
            "Raw Materials": {
                "2025-03-31 00:00:00": null,
                "2024-03-31 00:00:00": 45241000000.0,
                "2023-03-31 00:00:00": 40898900000.0,
                "2022-03-31 00:00:00": 36237800000.0,
                "2021-03-31 00:00:00": 32368000000.0
            },
            "Other Receivables": {
                "2025-03-31 00:00:00": 14700000.0,
                "2024-03-31 00:00:00": 58481000000.0,
                "2023-03-31 00:00:00": 63698300000.0,
                "2022-03-31 00:00:00": 59273200000.0,
                "2021-03-31 00:00:00": null
            },
            "Taxes Receivable": {
                "2025-03-31 00:00:00": 3536200000.0,
                "2024-03-31 00:00:00": 4496100000.0,
                "2023-03-31 00:00:00": 4031400000.0,
                "2022-03-31 00:00:00": 1447400000.0,
                "2021-03-31 00:00:00": null
            },
            "Accounts Receivable": {
                "2025-03-31 00:00:00": 91163700000.0,
                "2024-03-31 00:00:00": 73923800000.0,
                "2023-03-31 00:00:00": 70334800000.0,
                "2022-03-31 00:00:00": 61080900000.0,
                "2021-03-31 00:00:00": null
            },
            "Cash Cash Equivalents And Short Term Investments": {
                "2025-03-31 00:00:00": 97864300000.0,
                "2024-03-31 00:00:00": 111337000000.0,
                "2023-03-31 00:00:00": 82332100000.0,
                "2022-03-31 00:00:00": 75655100000.0,
                "2021-03-31 00:00:00": null
            },
            "Other Short Term Investments": {
                "2025-03-31 00:00:00": 90729800000.0,
                "2024-03-31 00:00:00": 99273800000.0,
                "2023-03-31 00:00:00": 42875200000.0,
                "2022-03-31 00:00:00": 62646500000.0,
                "2021-03-31 00:00:00": null
            },
            "Cash And Cash Equivalents": {
                "2025-03-31 00:00:00": 7134500000.0,
                "2024-03-31 00:00:00": 12063200000.0,
                "2023-03-31 00:00:00": 39456900000.0,
                "2022-03-31 00:00:00": 13008600000.0,
                "2021-03-31 00:00:00": null
            },
            "Cash Equivalents": {
                "2025-03-31 00:00:00": null,
                "2024-03-31 00:00:00": 6148000000.0,
                "2023-03-31 00:00:00": 31039500000.0,
                "2022-03-31 00:00:00": 8890300000.0,
                "2021-03-31 00:00:00": 25277800000.0
            },
            "Cash Financial": {
                "2025-03-31 00:00:00": null,
                "2024-03-31 00:00:00": 5915200000.0,
                "2023-03-31 00:00:00": 8417400000.0,
                "2022-03-31 00:00:00": 4118300000.0,
                "2021-03-31 00:00:00": 5151200000.0
            }
        },
        "income_statement": {
            "Tax Effect Of Unusual Items": {
                "2025-03-31 00:00:00": 0.0,
                "2024-03-31 00:00:00": 0.0,
                "2023-03-31 00:00:00": -278781450.0,
                "2022-03-31 00:00:00": -41306040.0,
                "2021-03-31 00:00:00": null
            },
            "Tax Rate For Calcs": {
                "2025-03-31 00:00:00": 0.255226,
                "2024-03-31 00:00:00": 0.251243,
                "2023-03-31 00:00:00": 0.2505,
                "2022-03-31 00:00:00": 0.2564,
                "2021-03-31 00:00:00": null
            },
            "Normalized EBITDA": {
                "2025-03-31 00:00:00": 75760600000.0,
                "2024-03-31 00:00:00": 57165500000.0,
                "2023-03-31 00:00:00": 44776100000.0,
                "2022-03-31 00:00:00": 35881400000.0,
                "2021-03-31 00:00:00": null
            },
            "Total Unusual Items": {
                "2025-03-31 00:00:00": 0.0,
                "2024-03-31 00:00:00": 0.0,
                "2023-03-31 00:00:00": -1112900000.0,
                "2022-03-31 00:00:00": -161100000.0,
                "2021-03-31 00:00:00": null
            },
            "Total Unusual Items Excluding Goodwill": {
                "2025-03-31 00:00:00": 0.0,
                "2024-03-31 00:00:00": 0.0,
                "2023-03-31 00:00:00": -1112900000.0,
                "2022-03-31 00:00:00": -161100000.0,
                "2021-03-31 00:00:00": null
            },
            "Net Income From Continuing Operation Net Minority Interest": {
                "2025-03-31 00:00:00": 53214400000.0,
                "2024-03-31 00:00:00": 39845200000.0,
                "2023-03-31 00:00:00": 29844200000.0,
                "2022-03-31 00:00:00": 23988700000.0,
                "2021-03-31 00:00:00": null
            },
            "Reconciled Depreciation": {
                "2025-03-31 00:00:00": 4673800000.0,
                "2024-03-31 00:00:00": 4432000000.0,
                "2023-03-31 00:00:00": 4288200000.0,
                "2022-03-31 00:00:00": 4011300000.0,
                "2021-03-31 00:00:00": null
            },
            "Reconciled Cost Of Revenue": {
                "2025-03-31 00:00:00": 121872300000.0,
                "2024-03-31 00:00:00": 105763200000.0,
                "2023-03-31 00:00:00": 98372000000.0,
                "2022-03-31 00:00:00": 89106200000.0,
                "2021-03-31 00:00:00": null
            },
            "EBITDA": {
                "2025-03-31 00:00:00": 75760600000.0,
                "2024-03-31 00:00:00": 57165500000.0,
                "2023-03-31 00:00:00": 43663200000.0,
                "2022-03-31 00:00:00": 35720300000.0,
                "2021-03-31 00:00:00": null
            },
            "EBIT": {
                "2025-03-31 00:00:00": 71086800000.0,
                "2024-03-31 00:00:00": 52733500000.0,
                "2023-03-31 00:00:00": 39375000000.0,
                "2022-03-31 00:00:00": 31709000000.0,
                "2021-03-31 00:00:00": null
            },
            "Net Interest Income": {
                "2025-03-31 00:00:00": -96800000.0,
                "2024-03-31 00:00:00": -71400000.0,
                "2023-03-31 00:00:00": 2445500000.0,
                "2022-03-31 00:00:00": 1710000000.0,
                "2021-03-31 00:00:00": null
            },
            "Interest Expense": {
                "2025-03-31 00:00:00": 96800000.0,
                "2024-03-31 00:00:00": 71400000.0,
                "2023-03-31 00:00:00": 145900000.0,
                "2022-03-31 00:00:00": 46600000.0,
                "2021-03-31 00:00:00": null
            },
            "Interest Income": {
                "2025-03-31 00:00:00": null,
                "2024-03-31 00:00:00": 5872500000.0,
                "2023-03-31 00:00:00": 2633900000.0,
                "2022-03-31 00:00:00": 1795500000.0,
                "2021-03-31 00:00:00": 638800000.0
            },
            "Normalized Income": {
                "2025-03-31 00:00:00": 53214400000.0,
                "2024-03-31 00:00:00": 39845200000.0,
                "2023-03-31 00:00:00": 30678318550.0,
                "2022-03-31 00:00:00": 24108493960.0,
                "2021-03-31 00:00:00": null
            },
            "Net Income From Continuing And Discontinued Operation": {
                "2025-03-31 00:00:00": 53214400000.0,
                "2024-03-31 00:00:00": 39845200000.0,
                "2023-03-31 00:00:00": 29844200000.0,
                "2022-03-31 00:00:00": 23988700000.0,
                "2021-03-31 00:00:00": null
            },
            "Total Expenses": {
                "2025-03-31 00:00:00": 174024300000.0,
                "2024-03-31 00:00:00": 156650300000.0,
                "2023-03-31 00:00:00": 136311400000.0,
                "2022-03-31 00:00:00": 121254900000.0,
                "2021-03-31 00:00:00": null
            },
            "Rent Expense Supplemental": {
                "2025-03-31 00:00:00": null,
                "2024-03-31 00:00:00": 331700000.0,
                "2023-03-31 00:00:00": 317200000.0,
                "2022-03-31 00:00:00": 283700000.0,
                "2021-03-31 00:00:00": 273500000.0
            },
            "Diluted Average Shares": {
                "2025-03-31 00:00:00": 7309670330.0,
                "2024-03-31 00:00:00": 7311045872.0,
                "2023-03-31 00:00:00": 7309778829.0,
                "2022-03-31 00:00:00": 7309778829.0,
                "2021-03-31 00:00:00": null
            },
            "Basic Average Shares": {
                "2025-03-31 00:00:00": 7309670330.0,
                "2024-03-31 00:00:00": 7311045872.0,
                "2023-03-31 00:00:00": 7309778829.0,
                "2022-03-31 00:00:00": 7309778829.0,
                "2021-03-31 00:00:00": null
            },
            "Diluted EPS": {
                "2025-03-31 00:00:00": 7.28,
                "2024-03-31 00:00:00": 5.45,
                "2023-03-31 00:00:00": 4.09,
                "2022-03-31 00:00:00": 3.281727,
                "2021-03-31 00:00:00": null
            },
            "Basic EPS": {
                "2025-03-31 00:00:00": 7.28,
                "2024-03-31 00:00:00": 5.45,
                "2023-03-31 00:00:00": 4.09,
                "2022-03-31 00:00:00": 3.281727,
                "2021-03-31 00:00:00": null
            },
            "Diluted NI Availto Com Stockholders": {
                "2025-03-31 00:00:00": 53214400000.0,
                "2024-03-31 00:00:00": 39845200000.0,
                "2023-03-31 00:00:00": 29844200000.0,
                "2022-03-31 00:00:00": 23988700000.0,
                "2021-03-31 00:00:00": null
            },
            "Net Income Common Stockholders": {
                "2025-03-31 00:00:00": 53214400000.0,
                "2024-03-31 00:00:00": 39845200000.0,
                "2023-03-31 00:00:00": 29844200000.0,
                "2022-03-31 00:00:00": 23988700000.0,
                "2021-03-31 00:00:00": null
            },
            "Otherunder Preferred Stock Dividend": {
                "2025-03-31 00:00:00": 0.0,
                "2024-03-31 00:00:00": 0.0,
                "2023-03-31 00:00:00": 0.0,
                "2022-03-31 00:00:00": 0.0,
                "2021-03-31 00:00:00": null
            },
            "Net Income": {
                "2025-03-31 00:00:00": 53214400000.0,
                "2024-03-31 00:00:00": 39845200000.0,
                "2023-03-31 00:00:00": 29844200000.0,
                "2022-03-31 00:00:00": 23988700000.0,
                "2021-03-31 00:00:00": null
            },
            "Minority Interests": {
                "2025-03-31 00:00:00": -12400000.0,
                "2024-03-31 00:00:00": -7200000.0,
                "2023-03-31 00:00:00": -18200000.0,
                "2022-03-31 00:00:00": -13500000.0,
                "2021-03-31 00:00:00": null
            },
            "Net Income Including Noncontrolling Interests": {
                "2025-03-31 00:00:00": 53226800000.0,
                "2024-03-31 00:00:00": 39852400000.0,
                "2023-03-31 00:00:00": 29862400000.0,
                "2022-03-31 00:00:00": 24002200000.0,
                "2021-03-31 00:00:00": null
            },
            "Net Income Continuous Operations": {
                "2025-03-31 00:00:00": 53226800000.0,
                "2024-03-31 00:00:00": 39852400000.0,
                "2023-03-31 00:00:00": 29862400000.0,
                "2022-03-31 00:00:00": 24002200000.0,
                "2021-03-31 00:00:00": null
            },
            "Tax Provision": {
                "2025-03-31 00:00:00": 18118500000.0,
                "2024-03-31 00:00:00": 13231000000.0,
                "2023-03-31 00:00:00": 9825600000.0,
                "2022-03-31 00:00:00": 8117800000.0,
                "2021-03-31 00:00:00": null
            },
            "Pretax Income": {
                "2025-03-31 00:00:00": 70990000000.0,
                "2024-03-31 00:00:00": 52662100000.0,
                "2023-03-31 00:00:00": 39229100000.0,
                "2022-03-31 00:00:00": 31662400000.0,
                "2021-03-31 00:00:00": null
            },
            "Other Non Operating Income Expenses": {
                "2025-03-31 00:00:00": 7423600000.0,
                "2024-03-31 00:00:00": 6701400000.0,
                "2023-03-31 00:00:00": 102400000.0,
                "2022-03-31 00:00:00": 106200000.0,
                "2021-03-31 00:00:00": null
            },
            "Special Income Charges": {
                "2025-03-31 00:00:00": 0.0,
                "2024-03-31 00:00:00": 0.0,
                "2023-03-31 00:00:00": -1171600000.0,
                "2022-03-31 00:00:00": -219800000.0,
                "2021-03-31 00:00:00": null
            },
            "Other Special Charges": {
                "2025-03-31 00:00:00": null,
                "2024-03-31 00:00:00": -70200000.0,
                "2023-03-31 00:00:00": -15200000.0,
                "2022-03-31 00:00:00": -4500000.0,
                "2021-03-31 00:00:00": -12100000.0
            },
            "Write Off": {
                "2025-03-31 00:00:00": null,
                "2024-03-31 00:00:00": 1804900000.0,
                "2023-03-31 00:00:00": 937400000.0,
                "2022-03-31 00:00:00": 224300000.0,
                "2021-03-31 00:00:00": 289300000.0
            },
            "Impairment Of Capital Assets": {
                "2025-03-31 00:00:00": null,
                "2024-03-31 00:00:00": 966600000.0,
                "2023-03-31 00:00:00": 249400000.0,
                "2022-03-31 00:00:00": 0.0,
                "2021-03-31 00:00:00": 154300000.0
            },
            "Net Non Operating Interest Income Expense": {
                "2025-03-31 00:00:00": -96800000.0,
                "2024-03-31 00:00:00": -71400000.0,
                "2023-03-31 00:00:00": 2445500000.0,
                "2022-03-31 00:00:00": 1710000000.0,
                "2021-03-31 00:00:00": null
            },
            "Total Other Finance Cost": {
                "2025-03-31 00:00:00": null,
                "2024-03-31 00:00:00": 52000000.0,
                "2023-03-31 00:00:00": 42500000.0,
                "2022-03-31 00:00:00": 38900000.0,
                "2021-03-31 00:00:00": 38000000.0
            },
            "Interest Expense Non Operating": {
                "2025-03-31 00:00:00": 96800000.0,
                "2024-03-31 00:00:00": 71400000.0,
                "2023-03-31 00:00:00": 145900000.0,
                "2022-03-31 00:00:00": 46600000.0,
                "2021-03-31 00:00:00": null
            },
            "Interest Income Non Operating": {
                "2025-03-31 00:00:00": null,
                "2024-03-31 00:00:00": 5872500000.0,
                "2023-03-31 00:00:00": 2633900000.0,
                "2022-03-31 00:00:00": 1795500000.0,
                "2021-03-31 00:00:00": 638800000.0
            },
            "Operating Income": {
                "2025-03-31 00:00:00": 63663200000.0,
                "2024-03-31 00:00:00": 46032100000.0,
                "2023-03-31 00:00:00": 37730400000.0,
                "2022-03-31 00:00:00": 29592500000.0,
                "2021-03-31 00:00:00": null
            },
            "Operating Expense": {
                "2025-03-31 00:00:00": 52152000000.0,
                "2024-03-31 00:00:00": 50887100000.0,
                "2023-03-31 00:00:00": 37939400000.0,
                "2022-03-31 00:00:00": 32148700000.0,
                "2021-03-31 00:00:00": null
            },
            "Other Operating Expenses": {
                "2025-03-31 00:00:00": 19871900000.0,
                "2024-03-31 00:00:00": 21560200000.0,
                "2023-03-31 00:00:00": 11846000000.0,
                "2022-03-31 00:00:00": 8221800000.0,
                "2021-03-31 00:00:00": null
            },
            "Depreciation And Amortization In Income Statement": {
                "2025-03-31 00:00:00": 4673800000.0,
                "2024-03-31 00:00:00": 4432000000.0,
                "2023-03-31 00:00:00": 4288200000.0,
                "2022-03-31 00:00:00": 4011300000.0,
                "2021-03-31 00:00:00": null
            },
            "Amortization": {
                "2025-03-31 00:00:00": null,
                "2024-03-31 00:00:00": 439800000.0,
                "2023-03-31 00:00:00": 318700000.0,
                "2022-03-31 00:00:00": 271800000.0,
                "2021-03-31 00:00:00": 199700000.0
            },
            "Depreciation Income Statement": {
                "2025-03-31 00:00:00": 4673800000.0,
                "2024-03-31 00:00:00": 4432000000.0,
                "2023-03-31 00:00:00": 3969500000.0,
                "2022-03-31 00:00:00": 3739500000.0,
                "2021-03-31 00:00:00": null
            },
            "Selling General And Administration": {
                "2025-03-31 00:00:00": null,
                "2024-03-31 00:00:00": 640800000.0,
                "2023-03-31 00:00:00": 582500000.0,
                "2022-03-31 00:00:00": 483400000.0,
                "2021-03-31 00:00:00": 417700000.0
            },
            "Selling And Marketing Expense": {
                "2025-03-31 00:00:00": null,
                "2024-03-31 00:00:00": 284600000.0,
                "2023-03-31 00:00:00": 189500000.0,
                "2022-03-31 00:00:00": 153900000.0,
                "2021-03-31 00:00:00": 78200000.0
            },
            "General And Administrative Expense": {
                "2025-03-31 00:00:00": null,
                "2024-03-31 00:00:00": 356200000.0,
                "2023-03-31 00:00:00": 393000000.0,
                "2022-03-31 00:00:00": 329500000.0,
                "2021-03-31 00:00:00": 339500000.0
            },
            "Rent And Landing Fees": {
                "2025-03-31 00:00:00": null,
                "2024-03-31 00:00:00": 331700000.0,
                "2023-03-31 00:00:00": 317200000.0,
                "2022-03-31 00:00:00": 283700000.0,
                "2021-03-31 00:00:00": 273500000.0
            },
            "Gross Profit": {
                "2025-03-31 00:00:00": 115815200000.0,
                "2024-03-31 00:00:00": 96919200000.0,
                "2023-03-31 00:00:00": 75669800000.0,
                "2022-03-31 00:00:00": 61741200000.0,
                "2021-03-31 00:00:00": null
            },
            "Cost Of Revenue": {
                "2025-03-31 00:00:00": 121872300000.0,
                "2024-03-31 00:00:00": 105763200000.0,
                "2023-03-31 00:00:00": 98372000000.0,
                "2022-03-31 00:00:00": 89106200000.0,
                "2021-03-31 00:00:00": null
            },
            "Total Revenue": {
                "2025-03-31 00:00:00": 237687500000.0,
                "2024-03-31 00:00:00": 202682400000.0,
                "2023-03-31 00:00:00": 174041800000.0,
                "2022-03-31 00:00:00": 150847400000.0,
                "2021-03-31 00:00:00": null
            },
            "Operating Revenue": {
                "2025-03-31 00:00:00": 237687500000.0,
                "2024-03-31 00:00:00": 202682400000.0,
                "2023-03-31 00:00:00": 174041800000.0,
                "2022-03-31 00:00:00": 150847400000.0,
                "2021-03-31 00:00:00": null
            }
        },
        "cash_flow": {
            "Free Cash Flow": {
                "2025-03-31 00:00:00": -4246600000.0,
                "2024-03-31 00:00:00": 40069600000.0,
                "2023-03-31 00:00:00": 6088100000.0,
                "2022-03-31 00:00:00": 36526600000.0,
                "2021-03-31 00:00:00": null
            },
            "Capital Expenditure": {
                "2025-03-31 00:00:00": -10112800000.0,
                "2024-03-31 00:00:00": -6525300000.0,
                "2023-03-31 00:00:00": -5904500000.0,
                "2022-03-31 00:00:00": -5545600000.0,
                "2021-03-31 00:00:00": null
            },
            "End Cash Position": {
                "2025-03-31 00:00:00": 7134500000.0,
                "2024-03-31 00:00:00": 12063200000.0,
                "2023-03-31 00:00:00": 39456900000.0,
                "2022-03-31 00:00:00": 13008600000.0,
                "2021-03-31 00:00:00": null
            },
            "Beginning Cash Position": {
                "2025-03-31 00:00:00": 12063200000.0,
                "2024-03-31 00:00:00": 39456900000.0,
                "2023-03-31 00:00:00": 13008600000.0,
                "2022-03-31 00:00:00": 30429000000.0,
                "2021-03-31 00:00:00": null
            },
            "Changes In Cash": {
                "2025-03-31 00:00:00": -4928700000.0,
                "2024-03-31 00:00:00": -27393700000.0,
                "2023-03-31 00:00:00": 26448300000.0,
                "2022-03-31 00:00:00": -17420400000.0,
                "2021-03-31 00:00:00": null
            },
            "Financing Cash Flow": {
                "2025-03-31 00:00:00": -16964300000.0,
                "2024-03-31 00:00:00": -14750100000.0,
                "2023-03-31 00:00:00": -12620800000.0,
                "2022-03-31 00:00:00": -10776000000.0,
                "2021-03-31 00:00:00": null
            },
            "Net Other Financing Charges": {
                "2025-03-31 00:00:00": null,
                "2024-03-31 00:00:00": null,
                "2023-03-31 00:00:00": -507900000.0,
                "2022-03-31 00:00:00": -475700000.0,
                "2021-03-31 00:00:00": -367000000.0
            },
            "Interest Paid Cff": {
                "2025-03-31 00:00:00": -96800000.0,
                "2024-03-31 00:00:00": -71400000.0,
                "2023-03-31 00:00:00": -149500000.0,
                "2022-03-31 00:00:00": -50500000.0,
                "2021-03-31 00:00:00": null
            },
            "Cash Dividends Paid": {
                "2025-03-31 00:00:00": -16807800000.0,
                "2024-03-31 00:00:00": -14620900000.0,
                "2023-03-31 00:00:00": -12428000000.0,
                "2022-03-31 00:00:00": -10233100000.0,
                "2021-03-31 00:00:00": null
            },
            "Common Stock Dividend Paid": {
                "2025-03-31 00:00:00": null,
                "2024-03-31 00:00:00": null,
                "2023-03-31 00:00:00": -12428000000.0,
                "2022-03-31 00:00:00": -10233100000.0,
                "2021-03-31 00:00:00": null
            },
            "Net Issuance Payments Of Debt": {
                "2025-03-31 00:00:00": null,
                "2024-03-31 00:00:00": null,
                "2023-03-31 00:00:00": null,
                "2022-03-31 00:00:00": 0.0,
                "2021-03-31 00:00:00": -83300000.0
            },
            "Net Long Term Debt Issuance": {
                "2025-03-31 00:00:00": null,
                "2024-03-31 00:00:00": null,
                "2023-03-31 00:00:00": null,
                "2022-03-31 00:00:00": 0.0,
                "2021-03-31 00:00:00": -83300000.0
            },
            "Investing Cash Flow": {
                "2025-03-31 00:00:00": 6169400000.0,
                "2024-03-31 00:00:00": -59238500000.0,
                "2023-03-31 00:00:00": 27076500000.0,
                "2022-03-31 00:00:00": -48716600000.0,
                "2021-03-31 00:00:00": null
            },
            "Net Other Investing Changes": {
                "2025-03-31 00:00:00": 700000.0,
                "2024-03-31 00:00:00": 1000000.0,
                "2023-03-31 00:00:00": 22800000.0,
                "2022-03-31 00:00:00": null,
                "2021-03-31 00:00:00": null
            },
            "Interest Received Cfi": {
                "2025-03-31 00:00:00": 6734400000.0,
                "2024-03-31 00:00:00": 4426000000.0,
                "2023-03-31 00:00:00": 2776900000.0,
                "2022-03-31 00:00:00": 1764500000.0,
                "2021-03-31 00:00:00": null
            },
            "Net Investment Purchase And Sale": {
                "2025-03-31 00:00:00": 9516600000.0,
                "2024-03-31 00:00:00": -57225500000.0,
                "2023-03-31 00:00:00": 30164300000.0,
                "2022-03-31 00:00:00": -45009500000.0,
                "2021-03-31 00:00:00": null
            },
            "Purchase Of Investment": {
                "2025-03-31 00:00:00": null,
                "2024-03-31 00:00:00": null,
                "2023-03-31 00:00:00": null,
                "2022-03-31 00:00:00": -45009500000.0,
                "2021-03-31 00:00:00": -21878000000.0
            },
            "Net PPE Purchase And Sale": {
                "2025-03-31 00:00:00": -10082300000.0,
                "2024-03-31 00:00:00": -6440000000.0,
                "2023-03-31 00:00:00": -5887500000.0,
                "2022-03-31 00:00:00": -5471600000.0,
                "2021-03-31 00:00:00": null
            },
            "Sale Of PPE": {
                "2025-03-31 00:00:00": 30500000.0,
                "2024-03-31 00:00:00": 85300000.0,
                "2023-03-31 00:00:00": 17000000.0,
                "2022-03-31 00:00:00": 74000000.0,
                "2021-03-31 00:00:00": null
            },
            "Purchase Of PPE": {
                "2025-03-31 00:00:00": -10112800000.0,
                "2024-03-31 00:00:00": -6525300000.0,
                "2023-03-31 00:00:00": -5904500000.0,
                "2022-03-31 00:00:00": -5545600000.0,
                "2021-03-31 00:00:00": null
            },
            "Operating Cash Flow": {
                "2025-03-31 00:00:00": 5866200000.0,
                "2024-03-31 00:00:00": 46594900000.0,
                "2023-03-31 00:00:00": 11992600000.0,
                "2022-03-31 00:00:00": 42072200000.0,
                "2021-03-31 00:00:00": null
            },
            "Taxes Refund Paid": {
                "2025-03-31 00:00:00": -16746400000.0,
                "2024-03-31 00:00:00": -14183700000.0,
                "2023-03-31 00:00:00": -10673300000.0,
                "2022-03-31 00:00:00": -8042900000.0,
                "2021-03-31 00:00:00": null
            },
            "Change In Working Capital": {
                "2025-03-31 00:00:00": -47102600000.0,
                "2024-03-31 00:00:00": 8180600000.0,
                "2023-03-31 00:00:00": -25342300000.0,
                "2022-03-31 00:00:00": 15338800000.0,
                "2021-03-31 00:00:00": null
            },
            "Change In Other Current Liabilities": {
                "2025-03-31 00:00:00": -19378600000.0,
                "2024-03-31 00:00:00": 10242900000.0,
                "2023-03-31 00:00:00": 8171500000.0,
                "2022-03-31 00:00:00": 26670400000.0,
                "2021-03-31 00:00:00": null
            },
            "Change In Other Current Assets": {
                "2025-03-31 00:00:00": 10011400000.0,
                "2024-03-31 00:00:00": 6573500000.0,
                "2023-03-31 00:00:00": 290700000.0,
                "2022-03-31 00:00:00": -11891500000.0,
                "2021-03-31 00:00:00": null
            },
            "Change In Payable": {
                "2025-03-31 00:00:00": -3675400000.0,
                "2024-03-31 00:00:00": 3755600000.0,
                "2023-03-31 00:00:00": -388900000.0,
                "2022-03-31 00:00:00": 704500000.0,
                "2021-03-31 00:00:00": null
            },
            "Change In Inventory": {
                "2025-03-31 00:00:00": -16720900000.0,
                "2024-03-31 00:00:00": -9929800000.0,
                "2023-03-31 00:00:00": -10118800000.0,
                "2022-03-31 00:00:00": -6118800000.0,
                "2021-03-31 00:00:00": null
            },
            "Change In Receivables": {
                "2025-03-31 00:00:00": -17236500000.0,
                "2024-03-31 00:00:00": -3590600000.0,
                "2023-03-31 00:00:00": -13002700000.0,
                "2022-03-31 00:00:00": 3298700000.0,
                "2021-03-31 00:00:00": null
            },
            "Other Non Cash Items": {
                "2025-03-31 00:00:00": -6291300000.0,
                "2024-03-31 00:00:00": -5813800000.0,
                "2023-03-31 00:00:00": -2625800000.0,
                "2022-03-31 00:00:00": -1350500000.0,
                "2021-03-31 00:00:00": null
            },
            "Provisionand Write Offof Assets": {
                "2025-03-31 00:00:00": 0.0,
                "2024-03-31 00:00:00": 966600000.0,
                "2023-03-31 00:00:00": 6478000000.0,
                "2022-03-31 00:00:00": 0.0,
                "2021-03-31 00:00:00": null
            },
            "Depreciation And Amortization": {
                "2025-03-31 00:00:00": 4673800000.0,
                "2024-03-31 00:00:00": 4432000000.0,
                "2023-03-31 00:00:00": 4288200000.0,
                "2022-03-31 00:00:00": 4011300000.0,
                "2021-03-31 00:00:00": null
            },
            "Amortization Cash Flow": {
                "2025-03-31 00:00:00": null,
                "2024-03-31 00:00:00": 439800000.0,
                "2023-03-31 00:00:00": 318700000.0,
                "2022-03-31 00:00:00": 271800000.0,
                "2021-03-31 00:00:00": 199700000.0
            },
            "Depreciation": {
                "2025-03-31 00:00:00": 4673800000.0,
                "2024-03-31 00:00:00": 4432000000.0,
                "2023-03-31 00:00:00": 3969500000.0,
                "2022-03-31 00:00:00": 3739500000.0,
                "2021-03-31 00:00:00": null
            },
            "Gain Loss On Sale Of PPE": {
                "2025-03-31 00:00:00": -25500000.0,
                "2024-03-31 00:00:00": -70200000.0,
                "2023-03-31 00:00:00": -15200000.0,
                "2022-03-31 00:00:00": -4500000.0,
                "2021-03-31 00:00:00": null
            },
            "Net Income From Continuing Operations": {
                "2025-03-31 00:00:00": 71345300000.0,
                "2024-03-31 00:00:00": 53083400000.0,
                "2023-03-31 00:00:00": 39688000000.0,
                "2022-03-31 00:00:00": 32120000000.0,
                "2021-03-31 00:00:00": null
            }
        }
    },
    "sentiment_analysis": {
        "newsapi": {
            "positive": 0,
            "negative": 0,
            "neutral": 0
        },
        "gnews": {
            "positive": 0,
            "negative": 0,
            "neutral": 0
        },
        "reddit": {
            "positive": 0,
            "negative": 0,
            "neutral": 0
        },
        "google_news": {
            "positive": 3.0,
            "negative": 0,
            "neutral": 8.0
        },
        "aggregated": {
            "positive": 3.0,
            "negative": 0,
            "neutral": 8.0
        },
        "weighted_aggregated": {
            "positive": 7.800000000000001,
            "negative": 0.0,
            "neutral": 20.8,
            "total_weight": 11.31
        },
        "comprehensive_analysis": {
            "sentiment_strength": {
                "bullish": 0.6896551724137931,
                "bearish": 0.0,
                "neutral": 1.839080459770115
            },
            "confidence_score": 0.7272727272727273,
            "market_context_applied": 1.3,
            "sources_coverage": {
                "global_financial": true,
                "indian_focus": true,
                "broad_market": true,
                "social_sentiment": true
            }
        }
    },
    "mpt_metrics": {
        "annual_return": 0.6409953723001762,
        "annual_volatility": 0.35299563212820273,
        "sharpe_ratio": 1.6458996073049634,
        "beta": 1.5084241188452538,
        "alpha": 0.48311380848728114
    },
    "institutional_holders": {
        "institutional_ownership_pct": 0.52597,
        "insider_ownership_pct": 0.23648001
    },
    "mutual_fund_holders": {},
    "support_level": 303.638203742981,
    "resistance_level": 421.871100769043,
    "risk_level": "LOW",
    "timeframe": "MEDIUM_TERM",
    "explanation": "Recommendation for BHARAT ELECTRONICS LTD (BEL.NS): NEUTRAL\nCurrent Price: Rs.389.50\n\nBuy Score: 0.000, Sell Score: 0.000\n\nNeutral Factors:\n- Price is stable relative to moving averages.\n- Sentiment is balanced, with no strong bullish or bearish signals.\n\nRisk Assessment:\n- Volatility: 0.0132 (higher values indicate higher risk)\n- Sector: Industrials\n- Industry: Aerospace & Defense\n",
    "ml_analysis": {
        "success": true,
        "predicted_price": 383.44521107072205,
        "confidence": -0.08942120361043582,
        "mse": 132.25134303895192,
        "mae": 5.492568450404023,
        "r2_score": -0.08942120361043582,
        "best_ml_model": "stacking",
        "best_model_metrics": {
            "mse": 132.25134303895192,
            "mae": 5.492568450404023,
            "r2": -0.08942120361043582
        },
        "all_model_scores": {
            "xgb": {
                "mse": 154.23204415065518,
                "mae": 7.27135242038016,
                "r2": -0.2704873562185055,
                "prediction": 386.7712097167969
            },
            "lgb": {
                "mse": 152.14607480933793,
                "mae": 7.1811958733970425,
                "r2": -0.2533041716980806,
                "prediction": 386.94758470818533
            },
            "cb": {
                "mse": 136.99699979779126,
                "mae": 6.142579814536107,
                "r2": -0.12851357862407986,
                "prediction": 388.18470762842713
            },
            "et": {
                "mse": 140.83306891728836,
                "mae": 6.586805960380987,
                "r2": -0.1601132201949369,
                "prediction": 384.07816642042593
            },
            "svr": {
                "mse": 262.65757411761456,
                "mae": 11.334948467592547,
                "r2": -1.163643286770486,
                "prediction": 394.50466809393976
            },
            "mlp": {
                "mse": 886.2589385569224,
                "mae": 20.76130452359267,
                "r2": -6.300563135066378,
                "prediction": 370.96664935173004
            },
            "ensemble": {
                "mse": 159.1231449433442,
                "mae": 7.811903053278823,
                "r2": -0.310777827302658,
                "prediction": 385.24216152093
            },
            "stacking": {
                "mse": 132.25134303895192,
                "mae": 5.492568450404023,
                "r2": -0.08942120361043582,
                "prediction": 386.7285165129473
            }
        },
        "lstm_metrics": {
            "mse": 0.02390902489423752,
            "r2": -1.4403455257415771,
            "adv_mse": 0.03725971281528473,
            "adv_r2": -2.803023099899292
        },
        "transformer_metrics": {
            "mse": 0.01132933795452118,
            "r2": -0.1563624143600464,
            "adv_mse": 0.012153133749961853,
            "adv_r2": -0.24044561386108398
        },
        "rl_metrics": {
            "success": true,
            "recommendation": "HOLD",
            "performance_pct": 0.045,
            "final_net_worth": 100045.0,
            "average_reward": -330597.68090387416,
            "average_events_per_episode": 116.61,
            "actions_distribution": {
                "hold": 0.27882960413080893,
                "buy": 0.7194492254733219,
                "sell": 0.0017211703958691911
            },
            "epoch_logs": [
                {
                    "episode": 10,
                    "total_reward": 6171242.055587248,
                    "average_reward": 1337143.8067931095,
                    "events_triggered": 114
                },
                {
                    "episode": 20,
                    "total_reward": -9122270.40170047,
                    "average_reward": -2702494.3841702733,
                    "events_triggered": 128
                },
                {
                    "episode": 30,
                    "total_reward": 1142768.7211416466,
                    "average_reward": 1212032.3119367403,
                    "events_triggered": 122
                },
                {
                    "episode": 40,
                    "total_reward": 1046159.2784618394,
                    "average_reward": -1092654.053239507,
                    "events_triggered": 114
                },
                {
                    "episode": 50,
                    "total_reward": 554377.6154504542,
                    "average_reward": -119015.6678333168,
                    "events_triggered": 105
                },
                {
                    "episode": 60,
                    "total_reward": -433397.1202987281,
                    "average_reward": -411712.70431785146,
                    "events_triggered": 114
                },
                {
                    "episode": 70,
                    "total_reward": 2230253.974365855,
                    "average_reward": -939175.1624095642,
                    "events_triggered": 128
                },
                {
                    "episode": 80,
                    "total_reward": -160466.5847059299,
                    "average_reward": -16432.13330541779,
                    "events_triggered": 100
                },
                {
                    "episode": 90,
                    "total_reward": -155063.63097206433,
                    "average_reward": -320642.13597467885,
                    "events_triggered": 119
                },
                {
                    "episode": 100,
                    "total_reward": -120599.18352116193,
                    "average_reward": -253026.68651798237,
                    "events_triggered": 119
                }
            ]
        },
        "ensemble_components": {
            "best_ml_model": 386.7285165129473,
            "lstm": 378.588134765625,
            "transformer": 385.01898193359375,
            "ensemble_average": 385.4279579941728
        },
        "industry_level_features": {
            "top_5_ml_models": [
                "xgb",
                "lgb",
                "cb",
                "et",
                "svr",
                "mlp",
                "ensemble",
                "stacking"
            ],
            "ensemble_methods": [
                "VotingRegressor",
                "StackingRegressor"
            ],
            "advanced_scaling": "RobustScaler",
            "model_selection": "Best R2 Score"
        }
    },
    "timestamp": "2025-08-06 12:50:12"
}